{
  "places": [
    {
      "name": "places/ChIJ11YilDM2jzARJS4xinFB-0Q",
      "id": "ChIJ11YilDM2jzARJS4xinFB-0Q",
      "types": [
        "resort_hotel",
        "tourist_attraction",
        "travel_agency",
        "hotel",
        "lodging",
        "restaurant",
        "food",
        "point_of_interest",
        "establishment"
      ],
      "nationalPhoneNumber": "094342 80628",
      "internationalPhoneNumber": "+91 94342 80628",
      "formattedAddress": "Sundergarh Village Baratang Island, Andaman and Nicobar Islands 744210, India",
      "addressComponents": [
        {
          "longText": "North and Middle Andaman",
          "shortText": "North and Middle Andaman",
          "types": [
            "administrative_area_level_3",
            "political"
          ],
          "languageCode": "en"
        },
        {
          "longText": "Andaman and Nicobar Islands",
          "shortText": "AN",
          "types": [
            "administrative_area_level_1",
            "political"
          ],
          "languageCode": "en"
        },
        {
          "longText": "India",
          "shortText": "IN",
          "types": [
            "country",
            "political"
          ],
          "languageCode": "en"
        },
        {
          "longText": "744210",
          "shortText": "744210",
          "types": [
            "postal_code"
          ],
          "languageCode": "en-US"
        }
      ],
      "plusCode": {
        "globalCode": "7M4J5QRR+9Q",
        "compoundCode": "5QRR+9Q Nilambur, Andaman and Nicobar Islands, India"
      },
      "location": {
        "latitude": 12.1909619,
        "longitude": 92.7919462
      },
      "viewport": {
        "low": {
          "latitude": 12.189624619708496,
          "longitude": 92.790422769708485
        },
        "high": {
          "latitude": 12.192322580291501,
          "longitude": 92.7931207302915
        }
      },
      "rating": 4.7,
      "googleMapsUri": "https://maps.google.com/?cid=4970638569639063077",
      "websiteUri": "https://www.dewdaleresorts.online/",
      "utcOffsetMinutes": 330,
      "adrFormatAddress": "Sundergarh Village Baratang Island, \u003cspan class=\"region\"\u003eAndaman and Nicobar Islands\u003c/span\u003e \u003cspan class=\"postal-code\"\u003e744210\u003c/span\u003e, \u003cspan class=\"country-name\"\u003eIndia\u003c/span\u003e",
      "businessStatus": "OPERATIONAL",
      "userRatingCount": 149,
      "iconMaskBaseUri": "https://maps.gstatic.com/mapfiles/place_api/icons/v2/hotel_pinlet",
      "iconBackgroundColor": "#909CE1",
      "displayName": {
        "text": "Dew Dale Resorts, Baratang Island",
        "languageCode": "en"
      },
      "primaryTypeDisplayName": {
        "text": "Resort hotel",
        "languageCode": "en-US"
      },
      "currentSecondaryOpeningHours": [
        {
          "openNow": false,
          "periods": [
            {
              "open": {
                "day": 0,
                "hour": 7,
                "minute": 0,
                "date": {
                  "year": 2024,
                  "month": 4,
                  "day": 28
                }
              },
              "close": {
                "day": 0,
                "hour": 10,
                "minute": 0,
                "date": {
                  "year": 2024,
                  "month": 4,
                  "day": 28
                }
              }
            },
            {
              "open": {
                "day": 1,
                "hour": 7,
                "minute": 0,
                "date": {
                  "year": 2024,
                  "month": 4,
                  "day": 29
                }
              },
              "close": {
                "day": 1,
                "hour": 10,
                "minute": 0,
                "date": {
                  "year": 2024,
                  "month": 4,
                  "day": 29
                }
              }
            },
            {
              "open": {
                "day": 2,
                "hour": 7,
                "minute": 0,
                "date": {
                  "year": 2024,
                  "month": 4,
                  "day": 23
                }
              },
              "close": {
                "day": 2,
                "hour": 10,
                "minute": 0,
                "date": {
                  "year": 2024,
                  "month": 4,
                  "day": 23
                }
              }
            },
            {
              "open": {
                "day": 3,
                "hour": 7,
                "minute": 0,
                "date": {
                  "year": 2024,
                  "month": 4,
                  "day": 24
                }
              },
              "close": {
                "day": 3,
                "hour": 10,
                "minute": 0,
                "date": {
                  "year": 2024,
                  "month": 4,
                  "day": 24
                }
              }
            },
            {
              "open": {
                "day": 4,
                "hour": 7,
                "minute": 0,
                "date": {
                  "year": 2024,
                  "month": 4,
                  "day": 25
                }
              },
              "close": {
                "day": 4,
                "hour": 10,
                "minute": 0,
                "date": {
                  "year": 2024,
                  "month": 4,
                  "day": 25
                }
              }
            },
            {
              "open": {
                "day": 5,
                "hour": 7,
                "minute": 0,
                "date": {
                  "year": 2024,
                  "month": 4,
                  "day": 26
                }
              },
              "close": {
                "day": 5,
                "hour": 10,
                "minute": 0,
                "date": {
                  "year": 2024,
                  "month": 4,
                  "day": 26
                }
              }
            },
            {
              "open": {
                "day": 6,
                "hour": 7,
                "minute": 0,
                "date": {
                  "year": 2024,
                  "month": 4,
                  "day": 27
                }
              },
              "close": {
                "day": 6,
                "hour": 10,
                "minute": 0,
                "date": {
                  "year": 2024,
                  "month": 4,
                  "day": 27
                }
              }
            }
          ],
          "weekdayDescriptions": [
            "Monday: 7:00 – 10:00 AM",
            "Tuesday: 7:00 – 10:00 AM",
            "Wednesday: 7:00 – 10:00 AM",
            "Thursday: 7:00 – 10:00 AM",
            "Friday: 7:00 – 10:00 AM",
            "Saturday: 7:00 – 10:00 AM",
            "Sunday: 7:00 – 10:00 AM"
          ],
          "secondaryHoursType": "BREAKFAST"
        },
        {
          "openNow": false,
          "periods": [
            {
              "open": {
                "day": 0,
                "hour": 18,
                "minute": 30,
                "date": {
                  "year": 2024,
                  "month": 4,
                  "day": 28
                }
              },
              "close": {
                "day": 0,
                "hour": 21,
                "minute": 30,
                "date": {
                  "year": 2024,
                  "month": 4,
                  "day": 28
                }
              }
            },
            {
              "open": {
                "day": 1,
                "hour": 18,
                "minute": 30,
                "date": {
                  "year": 2024,
                  "month": 4,
                  "day": 29
                }
              },
              "close": {
                "day": 1,
                "hour": 21,
                "minute": 30,
                "date": {
                  "year": 2024,
                  "month": 4,
                  "day": 29
                }
              }
            },
            {
              "open": {
                "day": 2,
                "hour": 18,
                "minute": 30,
                "date": {
                  "year": 2024,
                  "month": 4,
                  "day": 23
                }
              },
              "close": {
                "day": 2,
                "hour": 21,
                "minute": 30,
                "date": {
                  "year": 2024,
                  "month": 4,
                  "day": 23
                }
              }
            },
            {
              "open": {
                "day": 3,
                "hour": 18,
                "minute": 30,
                "date": {
                  "year": 2024,
                  "month": 4,
                  "day": 24
                }
              },
              "close": {
                "day": 3,
                "hour": 21,
                "minute": 30,
                "date": {
                  "year": 2024,
                  "month": 4,
                  "day": 24
                }
              }
            },
            {
              "open": {
                "day": 4,
                "hour": 18,
                "minute": 30,
                "date": {
                  "year": 2024,
                  "month": 4,
                  "day": 25
                }
              },
              "close": {
                "day": 4,
                "hour": 21,
                "minute": 30,
                "date": {
                  "year": 2024,
                  "month": 4,
                  "day": 25
                }
              }
            },
            {
              "open": {
                "day": 5,
                "hour": 18,
                "minute": 30,
                "date": {
                  "year": 2024,
                  "month": 4,
                  "day": 26
                }
              },
              "close": {
                "day": 5,
                "hour": 21,
                "minute": 30,
                "date": {
                  "year": 2024,
                  "month": 4,
                  "day": 26
                }
              }
            },
            {
              "open": {
                "day": 6,
                "hour": 18,
                "minute": 30,
                "date": {
                  "year": 2024,
                  "month": 4,
                  "day": 27
                }
              },
              "close": {
                "day": 6,
                "hour": 21,
                "minute": 30,
                "date": {
                  "year": 2024,
                  "month": 4,
                  "day": 27
                }
              }
            }
          ],
          "weekdayDescriptions": [
            "Monday: 6:30 – 9:30 PM",
            "Tuesday: 6:30 – 9:30 PM",
            "Wednesday: 6:30 – 9:30 PM",
            "Thursday: 6:30 – 9:30 PM",
            "Friday: 6:30 – 9:30 PM",
            "Saturday: 6:30 – 9:30 PM",
            "Sunday: 6:30 – 9:30 PM"
          ],
          "secondaryHoursType": "DINNER"
        }
      ],
      "regularSecondaryOpeningHours": [
        {
          "openNow": false,
          "periods": [
            {
              "open": {
                "day": 0,
                "hour": 7,
                "minute": 0
              },
              "close": {
                "day": 0,
                "hour": 10,
                "minute": 0
              }
            },
            {
              "open": {
                "day": 1,
                "hour": 7,
                "minute": 0
              },
              "close": {
                "day": 1,
                "hour": 10,
                "minute": 0
              }
            },
            {
              "open": {
                "day": 2,
                "hour": 7,
                "minute": 0
              },
              "close": {
                "day": 2,
                "hour": 10,
                "minute": 0
              }
            },
            {
              "open": {
                "day": 3,
                "hour": 7,
                "minute": 0
              },
              "close": {
                "day": 3,
                "hour": 10,
                "minute": 0
              }
            },
            {
              "open": {
                "day": 4,
                "hour": 7,
                "minute": 0
              },
              "close": {
                "day": 4,
                "hour": 10,
                "minute": 0
              }
            },
            {
              "open": {
                "day": 5,
                "hour": 7,
                "minute": 0
              },
              "close": {
                "day": 5,
                "hour": 10,
                "minute": 0
              }
            },
            {
              "open": {
                "day": 6,
                "hour": 7,
                "minute": 0
              },
              "close": {
                "day": 6,
                "hour": 10,
                "minute": 0
              }
            }
          ],
          "weekdayDescriptions": [
            "Monday: 7:00 – 10:00 AM",
            "Tuesday: 7:00 – 10:00 AM",
            "Wednesday: 7:00 – 10:00 AM",
            "Thursday: 7:00 – 10:00 AM",
            "Friday: 7:00 – 10:00 AM",
            "Saturday: 7:00 – 10:00 AM",
            "Sunday: 7:00 – 10:00 AM"
          ],
          "secondaryHoursType": "BREAKFAST"
        },
        {
          "openNow": false,
          "periods": [
            {
              "open": {
                "day": 0,
                "hour": 18,
                "minute": 30
              },
              "close": {
                "day": 0,
                "hour": 21,
                "minute": 30
              }
            },
            {
              "open": {
                "day": 1,
                "hour": 18,
                "minute": 30
              },
              "close": {
                "day": 1,
                "hour": 21,
                "minute": 30
              }
            },
            {
              "open": {
                "day": 2,
                "hour": 18,
                "minute": 30
              },
              "close": {
                "day": 2,
                "hour": 21,
                "minute": 30
              }
            },
            {
              "open": {
                "day": 3,
                "hour": 18,
                "minute": 30
              },
              "close": {
                "day": 3,
                "hour": 21,
                "minute": 30
              }
            },
            {
              "open": {
                "day": 4,
                "hour": 18,
                "minute": 30
              },
              "close": {
                "day": 4,
                "hour": 21,
                "minute": 30
              }
            },
            {
              "open": {
                "day": 5,
                "hour": 18,
                "minute": 30
              },
              "close": {
                "day": 5,
                "hour": 21,
                "minute": 30
              }
            },
            {
              "open": {
                "day": 6,
                "hour": 18,
                "minute": 30
              },
              "close": {
                "day": 6,
                "hour": 21,
                "minute": 30
              }
            }
          ],
          "weekdayDescriptions": [
            "Monday: 6:30 – 9:30 PM",
            "Tuesday: 6:30 – 9:30 PM",
            "Wednesday: 6:30 – 9:30 PM",
            "Thursday: 6:30 – 9:30 PM",
            "Friday: 6:30 – 9:30 PM",
            "Saturday: 6:30 – 9:30 PM",
            "Sunday: 6:30 – 9:30 PM"
          ],
          "secondaryHoursType": "DINNER"
        }
      ],
      "primaryType": "resort_hotel",
      "shortFormattedAddress": "Sundergarh Village Baratang Island",
      "reviews": [
        {
          "name": "places/ChIJ11YilDM2jzARJS4xinFB-0Q/reviews/ChdDSUhNMG9nS0VJQ0FnSUNkc2RLNW13RRAB",
          "relativePublishTimeDescription": "2 months ago",
          "rating": 3,
          "text": {
            "text": "Stayed at this quiet hotel away from the city bustle. Both the manager and staff were super nice and went out of their way to help. The food was yummy too!\nHowever when the power went out in the area, they were slow to get their generator going, and we had to keep calling them. No food delivery to the room, which was a bummer.\nStill, it's a good place if you want some peace and quiet.",
            "languageCode": "en"
          },
          "originalText": {
            "text": "Stayed at this quiet hotel away from the city bustle. Both the manager and staff were super nice and went out of their way to help. The food was yummy too!\nHowever when the power went out in the area, they were slow to get their generator going, and we had to keep calling them. No food delivery to the room, which was a bummer.\nStill, it's a good place if you want some peace and quiet.",
            "languageCode": "en"
          },
          "authorAttribution": {
            "displayName": "Nav Preet",
            "uri": "https://www.google.com/maps/contrib/108104181347000186326/reviews",
            "photoUri": "https://lh3.googleusercontent.com/a/ACg8ocL35ZJdwCba4SNYcUJ6SAaEODsDbgLkkyR3at3A9QWWWWnLFA=s128-c0x00000000-cc-rp-mo"
          },
          "publishTime": "2024-02-16T01:44:30Z"
        },
        {
          "name": "places/ChIJ11YilDM2jzARJS4xinFB-0Q/reviews/ChdDSUhNMG9nS0VJQ0FnSUQxdGR2d29RRRAB",
          "relativePublishTimeDescription": "3 months ago",
          "rating": 5,
          "text": {
            "text": "This resort at Baratang is placed at such an awesome spot, far from the crowd and surrounded by greeneries. Loved this place. My little one said it was the best place we have stayed in Baratang. Baratang of Andaman is actually a remote area, where one have very limited options to put up, but we were happy and satisfied to have managed a cottage in Dew Dale. The staffs were very cordial and helpful. The foods were served fresh and hot. We stayed for a night in Dew Dale. I would highly recommend this resort at Baratang to my friends and family.",
            "languageCode": "en"
          },
          "originalText": {
            "text": "This resort at Baratang is placed at such an awesome spot, far from the crowd and surrounded by greeneries. Loved this place. My little one said it was the best place we have stayed in Baratang. Baratang of Andaman is actually a remote area, where one have very limited options to put up, but we were happy and satisfied to have managed a cottage in Dew Dale. The staffs were very cordial and helpful. The foods were served fresh and hot. We stayed for a night in Dew Dale. I would highly recommend this resort at Baratang to my friends and family.",
            "languageCode": "en"
          },
          "authorAttribution": {
            "displayName": "SHILA MUKHERJEE",
            "uri": "https://www.google.com/maps/contrib/114436156206891064562/reviews",
            "photoUri": "https://lh3.googleusercontent.com/a-/ALV-UjXHI5GSlu5QGMjZ9qO28odbzymexNE-4qAjiFLDhF9wLACS9217Jg=s128-c0x00000000-cc-rp-mo"
          },
          "publishTime": "2024-01-09T02:50:08Z"
        },
        {
          "name": "places/ChIJ11YilDM2jzARJS4xinFB-0Q/reviews/ChZDSUhNMG9nS0VJQ0FnSURWbnVIOEVBEAE",
          "relativePublishTimeDescription": "4 months ago",
          "rating": 5,
          "text": {
            "text": "We saw this property on Internet. Baratang people don’t stay there and make day visit. But we stayed at Dew Dale. It was the best decision as we were mesmerised with the pristine nature it offers. Limestone caves, parrot island were simply awesome. The owner Jessy is such a warm person who made our stay thoroughly pleasant. We thank entire Dew Dale team.",
            "languageCode": "en"
          },
          "originalText": {
            "text": "We saw this property on Internet. Baratang people don’t stay there and make day visit. But we stayed at Dew Dale. It was the best decision as we were mesmerised with the pristine nature it offers. Limestone caves, parrot island were simply awesome. The owner Jessy is such a warm person who made our stay thoroughly pleasant. We thank entire Dew Dale team.",
            "languageCode": "en"
          },
          "authorAttribution": {
            "displayName": "puneet sweetworld",
            "uri": "https://www.google.com/maps/contrib/112074556322575697454/reviews",
            "photoUri": "https://lh3.googleusercontent.com/a/ACg8ocKgT_nRRqF1YucilRBHlxKjWiVJgzJsOjdD4i4O0niGeAmWSA=s128-c0x00000000-cc-rp-mo"
          },
          "publishTime": "2023-12-13T05:40:15Z"
        },
        {
          "name": "places/ChIJ11YilDM2jzARJS4xinFB-0Q/reviews/ChZDSUhNMG9nS0VJQ0FnSUQxaExMZWZnEAE",
          "relativePublishTimeDescription": "3 months ago",
          "rating": 5,
          "text": {
            "text": "Dew Dale resorts was like an oasis of calm within the wilderness of Baratang. Mrs. Jessy our host is an amazing person and took great care of us. The location was great and very quiet. The food was amazing as well. The aloo parathas especially were just like home.",
            "languageCode": "en"
          },
          "originalText": {
            "text": "Dew Dale resorts was like an oasis of calm within the wilderness of Baratang. Mrs. Jessy our host is an amazing person and took great care of us. The location was great and very quiet. The food was amazing as well. The aloo parathas especially were just like home.",
            "languageCode": "en"
          },
          "authorAttribution": {
            "displayName": "Kunal Karnani",
            "uri": "https://www.google.com/maps/contrib/108730842013274828322/reviews",
            "photoUri": "https://lh3.googleusercontent.com/a/ACg8ocJEyXdCSicMrhbkK4QG1LRYCLlNmCLeyFhA5VKr73AqUA-gbg=s128-c0x00000000-cc-rp-mo"
          },
          "publishTime": "2024-01-05T09:04:17Z"
        },
        {
          "name": "places/ChIJ11YilDM2jzARJS4xinFB-0Q/reviews/ChdDSUhNMG9nS0VJQ0FnSUREb0p5anpRRRAB",
          "relativePublishTimeDescription": "2 weeks ago",
          "rating": 5,
          "text": {
            "text": "Amazing experience at Dew Dale Resorts.  Mrs Jessy Madam and her teams politeness, receptions, rooms and food are exceptionally good.  The staff Mr Hari Prasad and Pradeep are so kind and helpful always.  Hope to visit again the same resorts when we go next time.",
            "languageCode": "en"
          },
          "originalText": {
            "text": "Amazing experience at Dew Dale Resorts.  Mrs Jessy Madam and her teams politeness, receptions, rooms and food are exceptionally good.  The staff Mr Hari Prasad and Pradeep are so kind and helpful always.  Hope to visit again the same resorts when we go next time.",
            "languageCode": "en"
          },
          "authorAttribution": {
            "displayName": "MADAN KUMAR.K",
            "uri": "https://www.google.com/maps/contrib/110304314533401218129/reviews",
            "photoUri": "https://lh3.googleusercontent.com/a-/ALV-UjXeZ5gbnlNYu54-fANiMC_wK5f1qJ-wl0MQ1TUb8KLKMZxFb7y0=s128-c0x00000000-cc-rp-mo"
          },
          "publishTime": "2024-04-04T08:30:42Z"
        }
      ],
      "photos": [
        {
          "name": "places/ChIJ11YilDM2jzARJS4xinFB-0Q/photos/ATplDJZCWgiFKB6sNwlay0-tpgJQHDnRYPZ5gP6-odkZBeQmH_yYBp0WNgu4_meQSIiIJFDVZKRYpvj_hM4oWqlswzlh98U9VpGJAD4Tl5Cot8xc_H3O_-fYzHDzuj3-DGdXwnpjzXs9OGcnii0qZxUMnePvH8i73zpYvXfO",
          "widthPx": 1440,
          "heightPx": 810,
          "authorAttributions": [
            {
              "displayName": "Dew Dale Resorts, Baratang Island",
              "uri": "//maps.google.com/maps/contrib/114618734632067517071",
              "photoUri": "//lh3.googleusercontent.com/a-/ALV-UjXx4V72uuKP2ev6d_j1QWBf5xVMsyRbQuinE43PY9Jz71MSJX7H=s100-p-k-no-mo"
            }
          ]
        },
        {
          "name": "places/ChIJ11YilDM2jzARJS4xinFB-0Q/photos/ATplDJZEQNgNrGmD457iB9ex-678JkenY8TvvihjxgoAjSSxgO_9OjUNJ-hFxCwUg-_a0-VMfpdUopl9JbMad-qHX63DGhhQc9xQ8qhjrlZ4d8DUyPVJtPTDgPwsB-CbgBgk5KVwgpTCQVWeLRGpnSm52wo8FFIl6TfRDBGY",
          "widthPx": 1599,
          "heightPx": 1066,
          "authorAttributions": [
            {
              "displayName": "Dew Dale Resorts, Baratang Island",
              "uri": "//maps.google.com/maps/contrib/114618734632067517071",
              "photoUri": "//lh3.googleusercontent.com/a-/ALV-UjXx4V72uuKP2ev6d_j1QWBf5xVMsyRbQuinE43PY9Jz71MSJX7H=s100-p-k-no-mo"
            }
          ]
        },
        {
          "name": "places/ChIJ11YilDM2jzARJS4xinFB-0Q/photos/ATplDJbuyIkMPIXZE_6xQNYKyHPp9KuwiqSeYTtDarjFROIT56B5p4idCQHFATB-sEovEdXQNsK-u0frST0CWiNaVH5wM3LROx1_DZ6oqgQ2RnlP9HNkEEqEjRiVw60a6PVq-7iOqroZYpoX8oUL1nJllQzItOD14413kDnK",
          "widthPx": 3967,
          "heightPx": 2976,
          "authorAttributions": [
            {
              "displayName": "Dew Dale Resorts, Baratang Island",
              "uri": "//maps.google.com/maps/contrib/114618734632067517071",
              "photoUri": "//lh3.googleusercontent.com/a-/ALV-UjXx4V72uuKP2ev6d_j1QWBf5xVMsyRbQuinE43PY9Jz71MSJX7H=s100-p-k-no-mo"
            }
          ]
        },
        {
          "name": "places/ChIJ11YilDM2jzARJS4xinFB-0Q/photos/ATplDJbIOsitBtEFNQGu28UcXc1AmG8d6VpJbJN789tErnvP_SmihGpjVqd62SPcA5L3aoTWGJuP6xJUXjs3Qw24B0_KqsUd_03obtb6xgkXYe-6E9gxOCdPuPzczAwXTnmSjyP_8NIQkp4gTY-fW6uBClp3vtywmfffcgb5",
          "widthPx": 1500,
          "heightPx": 1000,
          "authorAttributions": [
            {
              "displayName": "Dew Dale Resorts, Baratang Island",
              "uri": "//maps.google.com/maps/contrib/114618734632067517071",
              "photoUri": "//lh3.googleusercontent.com/a-/ALV-UjXx4V72uuKP2ev6d_j1QWBf5xVMsyRbQuinE43PY9Jz71MSJX7H=s100-p-k-no-mo"
            }
          ]
        },
        {
          "name": "places/ChIJ11YilDM2jzARJS4xinFB-0Q/photos/ATplDJYN42RwmlnI8MLkfzRnqmqj6y_MyiNmSoaWfDrrgm0RuvZstOFEP6nZEBJl5Q5y_irCgfXHtetm0oHqLlj8AasbMbqCueKhm7kUjJIBVH1nt0CXDnHDbzrxMZibawJRL8sx8eRwnBzkV29TCp20yoMuD36V_cApFYDn",
          "widthPx": 1599,
          "heightPx": 1066,
          "authorAttributions": [
            {
              "displayName": "Dew Dale Resorts, Baratang Island",
              "uri": "//maps.google.com/maps/contrib/114618734632067517071",
              "photoUri": "//lh3.googleusercontent.com/a-/ALV-UjXx4V72uuKP2ev6d_j1QWBf5xVMsyRbQuinE43PY9Jz71MSJX7H=s100-p-k-no-mo"
            }
          ]
        },
        {
          "name": "places/ChIJ11YilDM2jzARJS4xinFB-0Q/photos/ATplDJa4ou4FLrmIDWmy4JTvUnXtXdX5qTxX40vvrlPZUHYbEBcJIBO51wR0dsHqE7v0T_oUyWB7RwKwJhfkZAVcEPZPuL0B91zTgXCb1Q3ZpzglyoMUwCmepHXU17JVZaYdkHpkFf9QBm7KG4FQ_jfHrdRPTBDnBoQ1mmjj",
          "widthPx": 720,
          "heightPx": 405,
          "authorAttributions": [
            {
              "displayName": "Dew Dale Resorts, Baratang Island",
              "uri": "//maps.google.com/maps/contrib/114618734632067517071",
              "photoUri": "//lh3.googleusercontent.com/a-/ALV-UjXx4V72uuKP2ev6d_j1QWBf5xVMsyRbQuinE43PY9Jz71MSJX7H=s100-p-k-no-mo"
            }
          ]
        },
        {
          "name": "places/ChIJ11YilDM2jzARJS4xinFB-0Q/photos/ATplDJZ1haNGpmakUEiiItDmqrS3q_2MR_XqbjAYOmNgtWlxgh69ocPEvzOlGdfbxB22VlBGp0YE4xQAg5RQdgTj_4czAMLguwJyrimJxQuC4mfSORr6QkUlvsx0vJeD3Qk9oE7kSj6dR_oylgPeb2LGh6rprRQwHPhaIIFP",
          "widthPx": 4192,
          "heightPx": 2784,
          "authorAttributions": [
            {
              "displayName": "Dew Dale Resorts, Baratang Island",
              "uri": "//maps.google.com/maps/contrib/114618734632067517071",
              "photoUri": "//lh3.googleusercontent.com/a-/ALV-UjXx4V72uuKP2ev6d_j1QWBf5xVMsyRbQuinE43PY9Jz71MSJX7H=s100-p-k-no-mo"
            }
          ]
        },
        {
          "name": "places/ChIJ11YilDM2jzARJS4xinFB-0Q/photos/ATplDJaGEP5Nd9yYaOaG9LizVQtFsx4keb1RETMS0gwcf9eBXVj8WvSSPuXABmVCl7uPKMqGdM_zAgMkf_NpJVP_tq7H14XX9zBVNBeHEcFYtHpCinVj1DY3yIFERwzp1yKqTdd3G8Hv7v1V6_HORhg7fVdfGzLn_vixYhek",
          "widthPx": 1440,
          "heightPx": 810,
          "authorAttributions": [
            {
              "displayName": "Dew Dale Resorts, Baratang Island",
              "uri": "//maps.google.com/maps/contrib/114618734632067517071",
              "photoUri": "//lh3.googleusercontent.com/a-/ALV-UjXx4V72uuKP2ev6d_j1QWBf5xVMsyRbQuinE43PY9Jz71MSJX7H=s100-p-k-no-mo"
            }
          ]
        },
        {
          "name": "places/ChIJ11YilDM2jzARJS4xinFB-0Q/photos/ATplDJZHoe6ABB_X_yQlVzImWijydnp46Dqb6Qp8NZsGRaZLV5NUDGMfgTpfj10kpXr2tAZ3ta2-vA9sKybyE_w8XIURlH7IFOsDLDaXzkRwYDlB10Ft0jQwEhiHCYfPL-unmcl3G9iI9471LNPXI6N5soqaAU57Op9lhRae",
          "widthPx": 1280,
          "heightPx": 576,
          "authorAttributions": [
            {
              "displayName": "Dew Dale Resorts, Baratang Island",
              "uri": "//maps.google.com/maps/contrib/114618734632067517071",
              "photoUri": "//lh3.googleusercontent.com/a-/ALV-UjXx4V72uuKP2ev6d_j1QWBf5xVMsyRbQuinE43PY9Jz71MSJX7H=s100-p-k-no-mo"
            }
          ]
        },
        {
          "name": "places/ChIJ11YilDM2jzARJS4xinFB-0Q/photos/ATplDJbxDHdEs6n8yZCjpwuWrkoMWsVmDY1UUKzebe8d8v5aQXgauPXzo2lzz_Yyik3N3PiNqAirKk2Y6FgW0g5xi5jm6gvaUADgEJcE9wN6nWUv-NQXmeIGJ-T_KiiobbhE_cRCqBACBmbLWuNtSnYQh6OCKxXKPjvyQD99",
          "widthPx": 4608,
          "heightPx": 2080,
          "authorAttributions": [
            {
              "displayName": "Dew Dale Resorts, Baratang Island",
              "uri": "//maps.google.com/maps/contrib/114618734632067517071",
              "photoUri": "//lh3.googleusercontent.com/a-/ALV-UjXx4V72uuKP2ev6d_j1QWBf5xVMsyRbQuinE43PY9Jz71MSJX7H=s100-p-k-no-mo"
            }
          ]
        }
      ],
      "goodForChildren": true
    },
    {
      "name": "places/ChIJM8cHhuA3jzARFb3ggA-oXcc",
      "id": "ChIJM8cHhuA3jzARFb3ggA-oXcc",
      "types": [
        "church",
        "place_of_worship",
        "point_of_interest",
        "establishment"
      ],
      "formattedAddress": "Baratang, Nilambur, Andaman and Nicobar Islands 744210, India",
      "addressComponents": [
        {
          "longText": "Baratang",
          "shortText": "Baratang",
          "types": [
            "subpremise"
          ],
          "languageCode": "en"
        },
        {
          "longText": "Nilambur",
          "shortText": "Nilambur",
          "types": [
            "locality",
            "political"
          ],
          "languageCode": "en"
        },
        {
          "longText": "North and Middle Andaman",
          "shortText": "North and Middle Andaman",
          "types": [
            "administrative_area_level_3",
            "political"
          ],
          "languageCode": "en"
        },
        {
          "longText": "Andaman and Nicobar Islands",
          "shortText": "AN",
          "types": [
            "administrative_area_level_1",
            "political"
          ],
          "languageCode": "en"
        },
        {
          "longText": "India",
          "shortText": "IN",
          "types": [
            "country",
            "political"
          ],
          "languageCode": "en"
        },
        {
          "longText": "744210",
          "shortText": "744210",
          "types": [
            "postal_code"
          ],
          "languageCode": "en-US"
        }
      ],
      "plusCode": {
        "globalCode": "7M4J5QJQ+XR",
        "compoundCode": "5QJQ+XR Nilambur, Andaman and Nicobar Islands, India"
      },
      "location": {
        "latitude": 12.1824487,
        "longitude": 92.789577999999992
      },
      "viewport": {
        "low": {
          "latitude": 12.180979069708497,
          "longitude": 92.788239919708474
        },
        "high": {
          "latitude": 12.183677030291502,
          "longitude": 92.7909378802915
        }
      },
      "rating": 3,
      "googleMapsUri": "https://maps.google.com/?cid=14365823170921938197",
      "utcOffsetMinutes": 330,
      "adrFormatAddress": "Baratang, \u003cspan class=\"locality\"\u003eNilambur\u003c/span\u003e, \u003cspan class=\"region\"\u003eAndaman and Nicobar Islands\u003c/span\u003e \u003cspan class=\"postal-code\"\u003e744210\u003c/span\u003e, \u003cspan class=\"country-name\"\u003eIndia\u003c/span\u003e",
      "businessStatus": "OPERATIONAL",
      "userRatingCount": 2,
      "iconMaskBaseUri": "https://maps.gstatic.com/mapfiles/place_api/icons/v2/worship_christian_pinlet",
      "iconBackgroundColor": "#7B9EB0",
      "displayName": {
        "text": "St.Alphonsa catholic Church, Sundergarh Baratang",
        "languageCode": "en"
      },
      "primaryTypeDisplayName": {
        "text": "Church",
        "languageCode": "en-US"
      },
      "primaryType": "church",
      "shortFormattedAddress": "Baratang, Nilambur",
      "reviews": [
        {
          "name": "places/ChIJM8cHhuA3jzARFb3ggA-oXcc/reviews/ChZDSUhNMG9nS0VJQ0FnSUNDMk5lN0lBEAE",
          "relativePublishTimeDescription": "3 years ago",
          "rating": 1,
          "text": {
            "text": "Beautiful ❤️ church at Sundergarh baratang",
            "languageCode": "en"
          },
          "originalText": {
            "text": "Beautiful ❤️ church at Sundergarh baratang",
            "languageCode": "en"
          },
          "authorAttribution": {
            "displayName": "Abhisekh Kullu",
            "uri": "https://www.google.com/maps/contrib/104559991997034072237/reviews",
            "photoUri": "https://lh3.googleusercontent.com/a-/ALV-UjXCfT-lqSqjRV_B1GHdvo2XqND-zkm8IinH_VQ1r9MVzD_JCoAqRA=s128-c0x00000000-cc-rp-mo-ba3"
          },
          "publishTime": "2020-08-10T17:41:07Z"
        },
        {
          "name": "places/ChIJM8cHhuA3jzARFb3ggA-oXcc/reviews/ChZDSUhNMG9nS0VJQ0FnSURDdHRLSmZ3EAE",
          "relativePublishTimeDescription": "3 years ago",
          "rating": 5,
          "text": {
            "text": "Orthodox 🙏🙏🙏",
            "languageCode": "en-US"
          },
          "originalText": {
            "text": "Православно🙏🙏🙏",
            "languageCode": "sr"
          },
          "authorAttribution": {
            "displayName": "Рябикин Роман",
            "uri": "https://www.google.com/maps/contrib/114319457840485010964/reviews",
            "photoUri": "https://lh3.googleusercontent.com/a-/ALV-UjUSD5mQbzBBT6r1QsP5tHQnryrVHHWJwwp-JUwlU37P_c6B5BQc=s128-c0x00000000-cc-rp-mo-ba3"
          },
          "publishTime": "2020-09-26T08:03:19Z"
        }
      ],
      "photos": [
        {
          "name": "places/ChIJM8cHhuA3jzARFb3ggA-oXcc/photos/ATplDJYxZzM0UvM7pkQlUhBHEmlagHylzYzvXb3w0cYsH9J3Y2hVnbPo2DBbPmXCed3aQzTGibf6JWaxBJXIeOoHu9Bt--jdbRiB5-0UqKCepfR0OFnRp6KXniBaP0Ae1YKbeA0ScNbUH8xuDCsPCOiSEKBremRUhtkMMnay",
          "widthPx": 4608,
          "heightPx": 3456,
          "authorAttributions": [
            {
              "displayName": "Abhisekh Kullu",
              "uri": "//maps.google.com/maps/contrib/104559991997034072237",
              "photoUri": "//lh3.googleusercontent.com/a-/ALV-UjXCfT-lqSqjRV_B1GHdvo2XqND-zkm8IinH_VQ1r9MVzD_JCoAqRA=s100-p-k-no-mo"
            }
          ]
        }
      ]
    },
    {
      "name": "places/ChIJPyIILa43jzARo6zW6F4uIVg",
      "id": "ChIJPyIILa43jzARo6zW6F4uIVg",
      "types": [
        "church",
        "place_of_worship",
        "point_of_interest",
        "establishment"
      ],
      "formattedAddress": "5QGQ+R95, Great Andaman Trunk Rd, Nilambur, Andaman and Nicobar Islands 744210, India",
      "addressComponents": [
        {
          "longText": "5QGQ+R95",
          "shortText": "5QGQ+R95",
          "types": [
            "plus_code"
          ],
          "languageCode": "en-US"
        },
        {
          "longText": "Great Andaman Trunk Road",
          "shortText": "Great Andaman Trunk Rd",
          "types": [
            "route"
          ],
          "languageCode": "en"
        },
        {
          "longText": "Nilambur",
          "shortText": "Nilambur",
          "types": [
            "locality",
            "political"
          ],
          "languageCode": "en"
        },
        {
          "longText": "North and Middle Andaman",
          "shortText": "North and Middle Andaman",
          "types": [
            "administrative_area_level_3",
            "political"
          ],
          "languageCode": "en"
        },
        {
          "longText": "Andaman and Nicobar Islands",
          "shortText": "AN",
          "types": [
            "administrative_area_level_1",
            "political"
          ],
          "languageCode": "en"
        },
        {
          "longText": "India",
          "shortText": "IN",
          "types": [
            "country",
            "political"
          ],
          "languageCode": "en"
        },
        {
          "longText": "744210",
          "shortText": "744210",
          "types": [
            "postal_code"
          ],
          "languageCode": "en-US"
        }
      ],
      "location": {
        "latitude": 12.176936200000002,
        "longitude": 92.7885017
      },
      "viewport": {
        "low": {
          "latitude": 12.1755726697085,
          "longitude": 92.787249419708488
        },
        "high": {
          "latitude": 12.178270630291504,
          "longitude": 92.789947380291508
        }
      },
      "googleMapsUri": "https://maps.google.com/?cid=6350407934737296547",
      "utcOffsetMinutes": 330,
      "adrFormatAddress": "5QGQ+R95, \u003cspan class=\"street-address\"\u003eGreat Andaman Trunk Rd\u003c/span\u003e, \u003cspan class=\"locality\"\u003eNilambur\u003c/span\u003e, \u003cspan class=\"region\"\u003eAndaman and Nicobar Islands\u003c/span\u003e \u003cspan class=\"postal-code\"\u003e744210\u003c/span\u003e, \u003cspan class=\"country-name\"\u003eIndia\u003c/span\u003e",
      "businessStatus": "OPERATIONAL",
      "iconMaskBaseUri": "https://maps.gstatic.com/mapfiles/place_api/icons/v2/worship_christian_pinlet",
      "iconBackgroundColor": "#7B9EB0",
      "displayName": {
        "text": "Rapha Church",
        "languageCode": "en"
      },
      "primaryTypeDisplayName": {
        "text": "Church",
        "languageCode": "en-US"
      },
      "primaryType": "church",
      "shortFormattedAddress": "5QGQ+R95, Great Andaman Trunk Rd, Nilambur"
    }
  ]
}

