{
  "places": [
    {
      "name": "places/ChIJB_HS6ZI-UDcRn6ZiXDOvxs0",
      "id": "ChIJB_HS6ZI-UDcRn6ZiXDOvxs0",
      "types": [
        "church",
        "place_of_worship",
        "point_of_interest",
        "establishment"
      ],
      "formattedAddress": "6644+C3Q, Meghalaya 793150, India",
      "addressComponents": [
        {
          "longText": "6644+C3Q",
          "shortText": "6644+C3Q",
          "types": [
            "plus_code"
          ],
          "languageCode": "en-US"
        },
        {
          "longText": "West Jaintia Hills",
          "shortText": "West Jaintia Hills",
          "types": [
            "administrative_area_level_3",
            "political"
          ],
          "languageCode": "en"
        },
        {
          "longText": "Shillong Division",
          "shortText": "Shillong Division",
          "types": [
            "administrative_area_level_2",
            "political"
          ],
          "languageCode": "en"
        },
        {
          "longText": "Meghalaya",
          "shortText": "ML",
          "types": [
            "administrative_area_level_1",
            "political"
          ],
          "languageCode": "en"
        },
        {
          "longText": "India",
          "shortText": "IN",
          "types": [
            "country",
            "political"
          ],
          "languageCode": "en"
        },
        {
          "longText": "793150",
          "shortText": "793150",
          "types": [
            "postal_code"
          ],
          "languageCode": "en-US"
        }
      ],
      "location": {
        "latitude": 25.2060867,
        "longitude": 92.2052461
      },
      "viewport": {
        "low": {
          "latitude": 25.204754169708494,
          "longitude": 92.203933069708484
        },
        "high": {
          "latitude": 25.2074521302915,
          "longitude": 92.20663103029149
        }
      },
      "rating": 3.8,
      "googleMapsUri": "https://maps.google.com/?cid=14827731458292098719",
      "regularOpeningHours": {
        "openNow": false,
        "periods": [
          {
            "open": {
              "day": 0,
              "hour": 6,
              "minute": 0
            },
            "close": {
              "day": 0,
              "hour": 20,
              "minute": 0
            }
          }
        ],
        "weekdayDescriptions": [
          "Monday: Closed",
          "Tuesday: Closed",
          "Wednesday: Closed",
          "Thursday: Closed",
          "Friday: Closed",
          "Saturday: Closed",
          "Sunday: 6:00 AM – 8:00 PM"
        ]
      },
      "utcOffsetMinutes": 330,
      "adrFormatAddress": "6644+C3Q, \u003cspan class=\"region\"\u003eMeghalaya\u003c/span\u003e \u003cspan class=\"postal-code\"\u003e793150\u003c/span\u003e, \u003cspan class=\"country-name\"\u003eIndia\u003c/span\u003e",
      "businessStatus": "OPERATIONAL",
      "userRatingCount": 9,
      "iconMaskBaseUri": "https://maps.gstatic.com/mapfiles/place_api/icons/v2/worship_christian_pinlet",
      "iconBackgroundColor": "#7B9EB0",
      "displayName": {
        "text": "Trangblang Presbyterian Church",
        "languageCode": "en"
      },
      "primaryTypeDisplayName": {
        "text": "Church",
        "languageCode": "en-US"
      },
      "currentOpeningHours": {
        "openNow": false,
        "periods": [
          {
            "open": {
              "day": 0,
              "hour": 6,
              "minute": 0,
              "date": {
                "year": 2024,
                "month": 4,
                "day": 28
              }
            },
            "close": {
              "day": 0,
              "hour": 20,
              "minute": 0,
              "date": {
                "year": 2024,
                "month": 4,
                "day": 28
              }
            }
          }
        ],
        "weekdayDescriptions": [
          "Monday: Closed",
          "Tuesday: Closed",
          "Wednesday: Closed",
          "Thursday: Closed",
          "Friday: Closed",
          "Saturday: Closed",
          "Sunday: 6:00 AM – 8:00 PM"
        ]
      },
      "primaryType": "church",
      "shortFormattedAddress": "6644+C3Q",
      "reviews": [
        {
          "name": "places/ChIJB_HS6ZI-UDcRn6ZiXDOvxs0/reviews/ChZDSUhNMG9nS0VJQ0FnSURncXU2Tk5BEAE",
          "relativePublishTimeDescription": "6 years ago",
          "rating": 5,
          "text": {
            "text": "It's on the hilltop and its in d middle of the village... it's a very refreshing place to visit..",
            "languageCode": "en"
          },
          "originalText": {
            "text": "It's on the hilltop and its in d middle of the village... it's a very refreshing place to visit..",
            "languageCode": "en"
          },
          "authorAttribution": {
            "displayName": "pynshailang dkhar",
            "uri": "https://www.google.com/maps/contrib/115562357221454274089/reviews",
            "photoUri": "https://lh3.googleusercontent.com/a-/ALV-UjXNV5KsbM7qBbfWW657nFhMhU8W4DgVGmI79N1ze1TtxI1WaLVy9Q=s128-c0x00000000-cc-rp-mo-ba2"
          },
          "publishTime": "2017-09-16T18:27:52Z"
        },
        {
          "name": "places/ChIJB_HS6ZI-UDcRn6ZiXDOvxs0/reviews/ChZDSUhNMG9nS0VJQ0FnSURNM29tMUlBEAE",
          "relativePublishTimeDescription": "4 years ago",
          "rating": 5,
          "text": {
            "text": "I like it because it is located at the hill top",
            "languageCode": "en"
          },
          "originalText": {
            "text": "I like it because it is located at the hill top",
            "languageCode": "en"
          },
          "authorAttribution": {
            "displayName": "Syenmur S Amse",
            "uri": "https://www.google.com/maps/contrib/102261526034846161342/reviews",
            "photoUri": "https://lh3.googleusercontent.com/a-/ALV-UjV6nqJ2XO1i1NLsdFxw9_AlKcjKS9yqvyVA8M7llntDZrQAC1gA=s128-c0x00000000-cc-rp-mo"
          },
          "publishTime": "2019-12-31T10:19:44Z"
        },
        {
          "name": "places/ChIJB_HS6ZI-UDcRn6ZiXDOvxs0/reviews/ChZDSUhNMG9nS0VJQ0FnSUNRMnFydkVREAE",
          "relativePublishTimeDescription": "5 years ago",
          "rating": 5,
          "text": {
            "text": "It's a good place with perfect atmosphere for worship.",
            "languageCode": "en"
          },
          "originalText": {
            "text": "It's a good place with perfect atmosphere for worship.",
            "languageCode": "en"
          },
          "authorAttribution": {
            "displayName": "Easing Dkhar",
            "uri": "https://www.google.com/maps/contrib/118366795487100529359/reviews",
            "photoUri": "https://lh3.googleusercontent.com/a-/ALV-UjXuU9Kia2xL2v81LZHsVw5GdRGEe140IHhrN0kEIjLGUvkzJoYy=s128-c0x00000000-cc-rp-mo"
          },
          "publishTime": "2018-09-03T12:01:18Z"
        },
        {
          "name": "places/ChIJB_HS6ZI-UDcRn6ZiXDOvxs0/reviews/ChdDSUhNMG9nS0VJQ0FnSUNzM3AzcjZRRRAB",
          "relativePublishTimeDescription": "4 years ago",
          "rating": 3,
          "authorAttribution": {
            "displayName": "Banylla Rymbui",
            "uri": "https://www.google.com/maps/contrib/112715738571488643898/reviews",
            "photoUri": "https://lh3.googleusercontent.com/a-/ALV-UjVO33k-kpjXMbYxz78N8B4k0AxHmRbB1Z2yMW56g52S07SSRsZbog=s128-c0x00000000-cc-rp-mo-ba2"
          },
          "publishTime": "2020-02-03T04:23:00Z"
        },
        {
          "name": "places/ChIJB_HS6ZI-UDcRn6ZiXDOvxs0/reviews/ChdDSUhNMG9nS0VJQ0FnSURBbC1xcnRRRRAB",
          "relativePublishTimeDescription": "6 years ago",
          "rating": 4,
          "authorAttribution": {
            "displayName": "Lynda Lynda",
            "uri": "https://www.google.com/maps/contrib/111819673971682585548/reviews",
            "photoUri": "https://lh3.googleusercontent.com/a/ACg8ocKOQQYFCgUNCEaiUD9WhaFdMw8VGmhQLH_KuZlUOJPCa8YuGg=s128-c0x00000000-cc-rp-mo"
          },
          "publishTime": "2018-01-18T13:02:03Z"
        }
      ],
      "photos": [
        {
          "name": "places/ChIJB_HS6ZI-UDcRn6ZiXDOvxs0/photos/ATplDJaz3R-N7VtQJT3HQ2SEe5GDZLnU9af2KyGd299TKDPJ1hh7WWiMkuTZrqy2z08idgxFNRVz9Ox9BfhmmVIdI9MdUQDuGl_s62ck7-AsHfvLxwmPPs18A57JbMbG4626zBSGJyO_jHUQ3ltwnhZYa-flXgyGiNb9hH3i",
          "widthPx": 1156,
          "heightPx": 650,
          "authorAttributions": [
            {
              "displayName": "Ahbhah Dkhar",
              "uri": "//maps.google.com/maps/contrib/104387972716644176781",
              "photoUri": "//lh3.googleusercontent.com/a-/ALV-UjXjT8wlHV_qlS82d_7DIoKwC3yWFeXsbCKyPg0mdUh5JjgaV9xg=s100-p-k-no-mo"
            }
          ]
        },
        {
          "name": "places/ChIJB_HS6ZI-UDcRn6ZiXDOvxs0/photos/ATplDJaydUsYHRNt_qWhbG-ft2NKRfF61BOYA2V94ozHZHDZPOdSVeJYvgJfiq4mUUffH7yd2v2A71daxfvW5C4ac5232nCy6lbjT8jILLI64CwIFNN5EgPBk0M2aVdxgESnkSmsthynChtR0T7n4NlBO2nd7OokAzfwRYli",
          "widthPx": 1280,
          "heightPx": 720,
          "authorAttributions": [
            {
              "displayName": "Lynda Dkhar",
              "uri": "//maps.google.com/maps/contrib/114939040252452272142",
              "photoUri": "//lh3.googleusercontent.com/a/ACg8ocIbSm5GRpguneiEH4Xg9bktYLkF3Zhl2TeeX1R2WFXSki6hGw=s100-p-k-no-mo"
            }
          ]
        },
        {
          "name": "places/ChIJB_HS6ZI-UDcRn6ZiXDOvxs0/photos/ATplDJY1ZzT3b-ZVnG2ujfCQF9yCcU5cB3Ct88iQAkwP9zOK6010ogpe6Sy9U7xeNa-dkVd1nua6O3tmuFrzqvNPTBqONSHl-fJ-_Hi6j5EDEtUX2P9faplx8dcp1D4Sdv_hWGNezAPsN73IguZ4i8Qjci9eLkMr6GiX7_kf",
          "widthPx": 1080,
          "heightPx": 810,
          "authorAttributions": [
            {
              "displayName": "Lynda Dkhar",
              "uri": "//maps.google.com/maps/contrib/114939040252452272142",
              "photoUri": "//lh3.googleusercontent.com/a/ACg8ocIbSm5GRpguneiEH4Xg9bktYLkF3Zhl2TeeX1R2WFXSki6hGw=s100-p-k-no-mo"
            }
          ]
        },
        {
          "name": "places/ChIJB_HS6ZI-UDcRn6ZiXDOvxs0/photos/ATplDJaVzQRWPLIlwcCXyXJEwRcKsljLdSp-1hB6PfGebDfEPUpuqs_xfjLCI8qW0ExLrBdjTYKnLgkFgKRDxwiIQn5_NOzD3N5WG_EZW-lURnw879k2--wx2IjFBszQdQoe74PbsokDrZoY5PWYKKB6Kz6XpPFgb7BX0bsV",
          "widthPx": 1280,
          "heightPx": 720,
          "authorAttributions": [
            {
              "displayName": "Lynda Dkhar",
              "uri": "//maps.google.com/maps/contrib/114939040252452272142",
              "photoUri": "//lh3.googleusercontent.com/a/ACg8ocIbSm5GRpguneiEH4Xg9bktYLkF3Zhl2TeeX1R2WFXSki6hGw=s100-p-k-no-mo"
            }
          ]
        },
        {
          "name": "places/ChIJB_HS6ZI-UDcRn6ZiXDOvxs0/photos/ATplDJZYEPs8pRhPw8wp7d5WVISLpVXunPzLbZmnRvfbxzJFvFhvoWc4HpPoYElgB-ADBYbITUZ80F2BytYRcEZbGnD9mnLlRZCetCaR2tjTgiIUafsVrOzO8epLWy7INxv_DWSuOIWplyRHE4joF5Em9VFoKwz6532cVxkb",
          "widthPx": 1080,
          "heightPx": 1920,
          "authorAttributions": [
            {
              "displayName": "Wang phai wang phi",
              "uri": "//maps.google.com/maps/contrib/103053499037539330953",
              "photoUri": "//lh3.googleusercontent.com/a/ACg8ocJu2tyDpGZU3iSDC0CtL2q4iNXs2phRozb7eSm6QeI5P8-Klw=s100-p-k-no-mo"
            }
          ]
        },
        {
          "name": "places/ChIJB_HS6ZI-UDcRn6ZiXDOvxs0/photos/ATplDJbmXynEq4C68WimtHcK2UaczpqqEJVjDOzY2imQgNRmFaP2thsdiCgcCiRcnKmlEjVX8d9kx4mr2bcHnwDnyi7nHxj3G5373GozXImjqLKxIaf6ClymEsaHph7LVq1zKZrYrhEGv7Jh30tBHeeuhIy6Fz_oPGB3W1kg",
          "widthPx": 2560,
          "heightPx": 1440,
          "authorAttributions": [
            {
              "displayName": "Lynda Dkhar",
              "uri": "//maps.google.com/maps/contrib/114939040252452272142",
              "photoUri": "//lh3.googleusercontent.com/a/ACg8ocIbSm5GRpguneiEH4Xg9bktYLkF3Zhl2TeeX1R2WFXSki6hGw=s100-p-k-no-mo"
            }
          ]
        },
        {
          "name": "places/ChIJB_HS6ZI-UDcRn6ZiXDOvxs0/photos/ATplDJabct-HoSEzFLuq8J1QQRhrcUGLIwS7rBFoyd7GNeswyUc3sZGMNSH5iC8fSmpa0DtRAYUS896jBZpJg2TYViVSLQghL3eXPzrJsX9Uiintiq8OKqgluQVgfUYLvaUvZeGC8CQ78PWNElGtdT673B2a9YkUYZyFgeZM",
          "widthPx": 3264,
          "heightPx": 1836,
          "authorAttributions": [
            {
              "displayName": "Mehibatip Shylla",
              "uri": "//maps.google.com/maps/contrib/113111193302767799378",
              "photoUri": "//lh3.googleusercontent.com/a/ACg8ocJeJ167BLPUU0rXL1tRv_8_qe4WIEG56DcCAwUxlCL4L2922A=s100-p-k-no-mo"
            }
          ]
        },
        {
          "name": "places/ChIJB_HS6ZI-UDcRn6ZiXDOvxs0/photos/ATplDJbdMjrNLLedecsx7izREed5ZL-ZmelfCAt4b1-aoPlxPZK6_c2YoGBDfq_7csRheKG3DDQJFYd0ZjfydtJKGU43UeV1JjlXCJRjedmy5t4pLZw9nVFPOF_9r9pFRRHkMYChJ9qpL6kcJK_t2O5yCG8cFRHuc2oG44P7",
          "widthPx": 4160,
          "heightPx": 3120,
          "authorAttributions": [
            {
              "displayName": "pynshailang dkhar",
              "uri": "//maps.google.com/maps/contrib/115562357221454274089",
              "photoUri": "//lh3.googleusercontent.com/a-/ALV-UjXNV5KsbM7qBbfWW657nFhMhU8W4DgVGmI79N1ze1TtxI1WaLVy9Q=s100-p-k-no-mo"
            }
          ]
        },
        {
          "name": "places/ChIJB_HS6ZI-UDcRn6ZiXDOvxs0/photos/ATplDJZm81e3_wG3soKGJVPbMow38CyTH1W8eGjqqZjpG3q5B4hTSvBUXNddW17fsbpAfZRK_nz5OiWqr8iUKIVJg03YrJtX8dIWfl0chq13csKWdA3jWx2yyoNDppqMYHB0F8VmERVm7Yt8XovEfELjrzHiHTEwGywhAl8C",
          "widthPx": 1280,
          "heightPx": 960,
          "authorAttributions": [
            {
              "displayName": "Ahbhah Dkhar",
              "uri": "//maps.google.com/maps/contrib/104387972716644176781",
              "photoUri": "//lh3.googleusercontent.com/a-/ALV-UjXjT8wlHV_qlS82d_7DIoKwC3yWFeXsbCKyPg0mdUh5JjgaV9xg=s100-p-k-no-mo"
            }
          ]
        },
        {
          "name": "places/ChIJB_HS6ZI-UDcRn6ZiXDOvxs0/photos/ATplDJYtvyTzs6t5ic075B_oF919SQl4IDBFIc66J339BLg9_QQ9ljcQVMx_jTaFFCoc13GoWD3zoOqB6e3GV48upwzUz4r-ewwnHqg7-DNbOKsMKwjRnGV_xdcZiPRxJh9lPgpug9LDVIWztiz3_ImZl3ruAB2-O2S_5Ewy",
          "widthPx": 1836,
          "heightPx": 3264,
          "authorAttributions": [
            {
              "displayName": "Shekh Forid",
              "uri": "//maps.google.com/maps/contrib/111434642051439292832",
              "photoUri": "//lh3.googleusercontent.com/a/ACg8ocKQh27ue2PwM9YIvvzZ5BJ4STyasfaDNrFJkkT0eNxBvwopqQ=s100-p-k-no-mo"
            }
          ]
        }
      ]
    },
    {
      "name": "places/ChIJPzUU0YA_UDcRSNTtbZnxzyw",
      "id": "ChIJPzUU0YA_UDcRSNTtbZnxzyw",
      "types": [
        "tourist_attraction",
        "point_of_interest",
        "establishment"
      ],
      "formattedAddress": "7635+CF5, Unnamed Road, Jowai, Meghalaya 793150, India",
      "addressComponents": [
        {
          "longText": "7635+CF5",
          "shortText": "7635+CF5",
          "types": [
            "plus_code"
          ],
          "languageCode": "en-US"
        },
        {
          "longText": "Unnamed Road",
          "shortText": "Unnamed Road",
          "types": [
            "route"
          ],
          "languageCode": "en"
        },
        {
          "longText": "Jowai",
          "shortText": "Jowai",
          "types": [
            "locality",
            "political"
          ],
          "languageCode": "en"
        },
        {
          "longText": "East Jaintia Hills",
          "shortText": "East Jaintia Hills",
          "types": [
            "administrative_area_level_3",
            "political"
          ],
          "languageCode": "en"
        },
        {
          "longText": "Shillong Division",
          "shortText": "Shillong Division",
          "types": [
            "administrative_area_level_2",
            "political"
          ],
          "languageCode": "en"
        },
        {
          "longText": "Meghalaya",
          "shortText": "ML",
          "types": [
            "administrative_area_level_1",
            "political"
          ],
          "languageCode": "en"
        },
        {
          "longText": "India",
          "shortText": "IN",
          "types": [
            "country",
            "political"
          ],
          "languageCode": "en"
        },
        {
          "longText": "793150",
          "shortText": "793150",
          "types": [
            "postal_code"
          ],
          "languageCode": "en-US"
        }
      ],
      "location": {
        "latitude": 25.2535031,
        "longitude": 92.208738799999992
      },
      "viewport": {
        "low": {
          "latitude": 25.252154119708496,
          "longitude": 92.2073898197085
        },
        "high": {
          "latitude": 25.2548520802915,
          "longitude": 92.2100877802915
        }
      },
      "rating": 4.6,
      "googleMapsUri": "https://maps.google.com/?cid=3229065099124528200",
      "utcOffsetMinutes": 330,
      "adrFormatAddress": "7635+CF5, \u003cspan class=\"street-address\"\u003eUnnamed Road\u003c/span\u003e, \u003cspan class=\"locality\"\u003eJowai\u003c/span\u003e, \u003cspan class=\"region\"\u003eMeghalaya\u003c/span\u003e \u003cspan class=\"postal-code\"\u003e793150\u003c/span\u003e, \u003cspan class=\"country-name\"\u003eIndia\u003c/span\u003e",
      "businessStatus": "OPERATIONAL",
      "userRatingCount": 5,
      "iconMaskBaseUri": "https://maps.gstatic.com/mapfiles/place_api/icons/v2/generic_pinlet",
      "iconBackgroundColor": "#13B5C7",
      "displayName": {
        "text": "Leshka Viewpoint",
        "languageCode": "en"
      },
      "primaryTypeDisplayName": {
        "text": "Tourist Attraction",
        "languageCode": "en-US"
      },
      "primaryType": "tourist_attraction",
      "shortFormattedAddress": "7635+CF5, Unnamed Road, Jowai",
      "reviews": [
        {
          "name": "places/ChIJPzUU0YA_UDcRSNTtbZnxzyw/reviews/ChdDSUhNMG9nS0VJQ0FnSUNkMGRlT3d3RRAB",
          "relativePublishTimeDescription": "2 months ago",
          "rating": 5,
          "text": {
            "text": "Beautiful dam in meghalaya .... And I celebrate there my birthday with my friend 😊💕",
            "languageCode": "en"
          },
          "originalText": {
            "text": "Beautiful dam in meghalaya .... And I celebrate there my birthday with my friend 😊💕",
            "languageCode": "en"
          },
          "authorAttribution": {
            "displayName": "KESHAB DAS",
            "uri": "https://www.google.com/maps/contrib/117472446514629579857/reviews",
            "photoUri": "https://lh3.googleusercontent.com/a-/ALV-UjW1DR7VS1wRjhhF_OBVbLbWTRJdR6TJGMqyLgULd0WPZ6mEM_MV=s128-c0x00000000-cc-rp-mo"
          },
          "publishTime": "2024-02-16T01:00:29Z"
        },
        {
          "name": "places/ChIJPzUU0YA_UDcRSNTtbZnxzyw/reviews/ChZDSUhNMG9nS0VJQ0FnSUQtc2F6LWJBEAE",
          "relativePublishTimeDescription": "a year ago",
          "rating": 5,
          "text": {
            "text": "Breathtaking location. Amazing viewpoint.",
            "languageCode": "en"
          },
          "originalText": {
            "text": "Breathtaking location. Amazing viewpoint.",
            "languageCode": "en"
          },
          "authorAttribution": {
            "displayName": "Mitesh Vishwakarma",
            "uri": "https://www.google.com/maps/contrib/117835802397976046635/reviews",
            "photoUri": "https://lh3.googleusercontent.com/a-/ALV-UjXkjdFCDaOE0cqUgyo-2cSQJgpjnF3xCV48piv0SRQtAmJnjxcN=s128-c0x00000000-cc-rp-mo"
          },
          "publishTime": "2022-12-02T13:59:56Z"
        },
        {
          "name": "places/ChIJPzUU0YA_UDcRSNTtbZnxzyw/reviews/ChdDSUhNMG9nS0VJQ0FnSURoMVo3YnpnRRAB",
          "relativePublishTimeDescription": "a year ago",
          "rating": 5,
          "text": {
            "text": "Nice",
            "languageCode": "en"
          },
          "originalText": {
            "text": "Nice",
            "languageCode": "en"
          },
          "authorAttribution": {
            "displayName": "Khurshid Alam",
            "uri": "https://www.google.com/maps/contrib/114065111443796140745/reviews",
            "photoUri": "https://lh3.googleusercontent.com/a-/ALV-UjXskm4COl1xnNzdI5vGrDFco0llVaZ87UnsvUPCMJqw8aQL-9Re=s128-c0x00000000-cc-rp-mo-ba4"
          },
          "publishTime": "2023-03-14T05:45:26Z"
        },
        {
          "name": "places/ChIJPzUU0YA_UDcRSNTtbZnxzyw/reviews/ChdDSUhNMG9nS0VJQ0FnSUNacTYyUXp3RRAB",
          "relativePublishTimeDescription": "7 months ago",
          "rating": 5,
          "authorAttribution": {
            "displayName": "Ramesh kumar Sunarcharya",
            "uri": "https://www.google.com/maps/contrib/103565935932585329785/reviews",
            "photoUri": "https://lh3.googleusercontent.com/a/ACg8ocLZwgyHdV1YF4lmxm5xLq16BdGuBMutimMKHObJqZR-aXjHaw=s128-c0x00000000-cc-rp-mo"
          },
          "publishTime": "2023-09-18T11:46:08Z"
        },
        {
          "name": "places/ChIJPzUU0YA_UDcRSNTtbZnxzyw/reviews/ChdDSUhNMG9nS0VJQ0FnSUNaa3I2Z3FRRRAB",
          "relativePublishTimeDescription": "7 months ago",
          "rating": 3,
          "authorAttribution": {
            "displayName": "Dickens Laloo",
            "uri": "https://www.google.com/maps/contrib/109576313465384494425/reviews",
            "photoUri": "https://lh3.googleusercontent.com/a-/ALV-UjWwDE30pAd8xwSFCUZp3gEf8fADZlo6Q8mkp513ULxeF9IABIwx=s128-c0x00000000-cc-rp-mo"
          },
          "publishTime": "2023-09-07T11:25:54Z"
        }
      ],
      "photos": [
        {
          "name": "places/ChIJPzUU0YA_UDcRSNTtbZnxzyw/photos/ATplDJZN4FxS0mnmQ7UiXtNPyvSfZCaVtv807YwazNaltkXD53ooM4rZre6R3vo2MKiwhCw3j-uTb46TZRO_GnrGvu1K8b7Bh_LWAHgt1yDSV2egg92B9VT71WsR-DeXwTDY2rN3HMSjcUI7bBDzFUXyrvmv1aQriYDYbRSY",
          "widthPx": 3264,
          "heightPx": 2448,
          "authorAttributions": [
            {
              "displayName": "Ramesh kumar Sunarcharya",
              "uri": "//maps.google.com/maps/contrib/103565935932585329785",
              "photoUri": "//lh3.googleusercontent.com/a/ACg8ocLZwgyHdV1YF4lmxm5xLq16BdGuBMutimMKHObJqZR-aXjHaw=s100-p-k-no-mo"
            }
          ]
        },
        {
          "name": "places/ChIJPzUU0YA_UDcRSNTtbZnxzyw/photos/ATplDJbFZWtjjdHmZ6x5Hh0_qC1yYl5_bSvE9Jk7M1Vcb4jhTmG0Vg41RBOZcPngjlikzv39YDR-M6wUe8KYLDRf7_TaRrJ-RgiwsBEWoI-MPi_bvx5jrvZo8BYBws30c8vUmxjWRETk6qnl_3BZ0UTeOFWVuBtsVED_y9_Q",
          "widthPx": 4032,
          "heightPx": 3024,
          "authorAttributions": [
            {
              "displayName": "samborlang wahlang",
              "uri": "//maps.google.com/maps/contrib/103274715730015658161",
              "photoUri": "//lh3.googleusercontent.com/a-/ALV-UjVEq9qukVvm-Podfu_5_qAd_CTGytAGQGa4qRrHrfb-HxO7FfLY=s100-p-k-no-mo"
            }
          ]
        },
        {
          "name": "places/ChIJPzUU0YA_UDcRSNTtbZnxzyw/photos/ATplDJZ88y-ormLxTXNKcjXq9kpRerfM2p7UhlGz8lOL8CKjYCPFnuXKvty8qPGSnrwzxpgPMY4cBHBHgnbUqrgn7_LiW5VgNp-qSVvNITeDGHNiHKf9doxfv_qhjY0ZiQ5mjN8FZwayXWxytUIjx0lXhMQ8Kf2iqTATE0xb",
          "widthPx": 4608,
          "heightPx": 2080,
          "authorAttributions": [
            {
              "displayName": "Mitesh Vishwakarma",
              "uri": "//maps.google.com/maps/contrib/117835802397976046635",
              "photoUri": "//lh3.googleusercontent.com/a-/ALV-UjXkjdFCDaOE0cqUgyo-2cSQJgpjnF3xCV48piv0SRQtAmJnjxcN=s100-p-k-no-mo"
            }
          ]
        },
        {
          "name": "places/ChIJPzUU0YA_UDcRSNTtbZnxzyw/photos/ATplDJYkEsCcw871LgITZiydbQgxSRCZ6jwzloycHp9pk3eL9HR677ZHgrbw2skJcprPcWq_PRTEILgZwscOsn7vzveM32SkNqQc1ju3CXdLtdLAL6wpvXBYmIt2iBRhuf0yxv2jljUkaSK1Lc_VQss43dAXrT1X4d8P_alQ",
          "widthPx": 6000,
          "heightPx": 4000,
          "authorAttributions": [
            {
              "displayName": "Rajesh Kenjale",
              "uri": "//maps.google.com/maps/contrib/112144099935973328890",
              "photoUri": "//lh3.googleusercontent.com/a-/ALV-UjXb9ZJI6VydEKpgGXQH0knsYDuuCpv6VClQSIFjyDcjtm2ZPFtf=s100-p-k-no-mo"
            }
          ]
        },
        {
          "name": "places/ChIJPzUU0YA_UDcRSNTtbZnxzyw/photos/ATplDJaKQeKiKctaktWUuG1xKilTVLraVs-wnv26QbLgHjWUlFI6-mpBkzM-B7mj2i6rHofE_iQpNOffeQcWwpL6qH7xKz8PJ9gnQ0wr8JYB_8r3sfFifuUwqYevWa9UDL3Ih65xfFSq5if0Ms2LAUUTzSSzRtds6YD_zOcy",
          "widthPx": 1800,
          "heightPx": 4000,
          "authorAttributions": [
            {
              "displayName": "Dickens Laloo",
              "uri": "//maps.google.com/maps/contrib/109576313465384494425",
              "photoUri": "//lh3.googleusercontent.com/a-/ALV-UjWwDE30pAd8xwSFCUZp3gEf8fADZlo6Q8mkp513ULxeF9IABIwx=s100-p-k-no-mo"
            }
          ]
        },
        {
          "name": "places/ChIJPzUU0YA_UDcRSNTtbZnxzyw/photos/ATplDJaHahUVZdMy1HVQefcbTFvZlvVoVbHHkwV3gmFzpWYYnKjIHvV5fWXLgnsKXxSrKY8P3LtvYv5dPTtU0GukO5mp21ZJWUDK-jRC61dwvZ7Nk77MTdYG03MhGA91FoC5GMRL3nFk1EGGpG_m_JO0wfEAcgWjuN5DpXKp",
          "widthPx": 4032,
          "heightPx": 3024,
          "authorAttributions": [
            {
              "displayName": "samborlang wahlang",
              "uri": "//maps.google.com/maps/contrib/103274715730015658161",
              "photoUri": "//lh3.googleusercontent.com/a-/ALV-UjVEq9qukVvm-Podfu_5_qAd_CTGytAGQGa4qRrHrfb-HxO7FfLY=s100-p-k-no-mo"
            }
          ]
        },
        {
          "name": "places/ChIJPzUU0YA_UDcRSNTtbZnxzyw/photos/ATplDJY-qcU9g_RXuiEQ90XsPS7TSnRlC1oum5y9I-HflSX5kXPoDcUCPm8t7fOlUU2lzcfl-kwjDKxch5C1dcvCdg49EYB5ABLLDnQVX4JKPuZlbMAE-rMW3RsuIqyzaqZzWJ_xSy_yorPCvA6ud1AQRVj3M8kXaTq6DpmF",
          "widthPx": 4608,
          "heightPx": 2080,
          "authorAttributions": [
            {
              "displayName": "Mitesh Vishwakarma",
              "uri": "//maps.google.com/maps/contrib/117835802397976046635",
              "photoUri": "//lh3.googleusercontent.com/a-/ALV-UjXkjdFCDaOE0cqUgyo-2cSQJgpjnF3xCV48piv0SRQtAmJnjxcN=s100-p-k-no-mo"
            }
          ]
        },
        {
          "name": "places/ChIJPzUU0YA_UDcRSNTtbZnxzyw/photos/ATplDJYEiP_gxVo_B3Xf4DdYJw3VGXDi1Un3KlgKgqALvc7OJa_aTXRGn2sG4cCa4z1aup0Q9OgaVdC9KUBjfdTmnPdOyo90Nk3UH7Y0ZB73fvmAKS1Y7bAxhnpi_bdFC8J_LGyjpF7K5WcyMXWMYZNw1Rh06FpOrb3aEyJj",
          "widthPx": 2448,
          "heightPx": 3264,
          "authorAttributions": [
            {
              "displayName": "KESHAB DAS",
              "uri": "//maps.google.com/maps/contrib/117472446514629579857",
              "photoUri": "//lh3.googleusercontent.com/a-/ALV-UjW1DR7VS1wRjhhF_OBVbLbWTRJdR6TJGMqyLgULd0WPZ6mEM_MV=s100-p-k-no-mo"
            }
          ]
        },
        {
          "name": "places/ChIJPzUU0YA_UDcRSNTtbZnxzyw/photos/ATplDJZZtEsqPShC2amq1RrEQiIt8m8H35dQivCw1xUBsa4hU8T_ubs-K0fRxD9Z3jEXQcpby8QITlSW_tPE-U9YaKOjx_4m5yCPLdIyWhqoU2d7VvYQxSirVE2_b2xflGczpWH_tabwoqPdAl0eW0kjdXLYVlMEvQaPcGDE",
          "widthPx": 2448,
          "heightPx": 3264,
          "authorAttributions": [
            {
              "displayName": "KESHAB DAS",
              "uri": "//maps.google.com/maps/contrib/117472446514629579857",
              "photoUri": "//lh3.googleusercontent.com/a-/ALV-UjW1DR7VS1wRjhhF_OBVbLbWTRJdR6TJGMqyLgULd0WPZ6mEM_MV=s100-p-k-no-mo"
            }
          ]
        },
        {
          "name": "places/ChIJPzUU0YA_UDcRSNTtbZnxzyw/photos/ATplDJbJH_yilgQ_Ybjhi77--pTObd9rKP9GlGMFd2zQAFKL54vcnm0x7oOnfRPToto-qhBt1WMnLuon5sepoNMk-S_Lk3XQwn1ehgSQxl86en3_jHPI1mlg48rkdI-2F4sBIxcEHp06I4SQFwgDe6Pscc8gTna1qxuoSM-L",
          "widthPx": 1440,
          "heightPx": 1932,
          "authorAttributions": [
            {
              "displayName": "KESHAB DAS",
              "uri": "//maps.google.com/maps/contrib/117472446514629579857",
              "photoUri": "//lh3.googleusercontent.com/a-/ALV-UjW1DR7VS1wRjhhF_OBVbLbWTRJdR6TJGMqyLgULd0WPZ6mEM_MV=s100-p-k-no-mo"
            }
          ]
        }
      ],
      "goodForChildren": true
    },
    {
      "name": "places/ChIJcxmz41Y9UDcR0Qi_Z_l4j8I",
      "id": "ChIJcxmz41Y9UDcR0Qi_Z_l4j8I",
      "types": [
        "church",
        "place_of_worship",
        "point_of_interest",
        "establishment"
      ],
      "formattedAddress": "66HW+JFJ, Bataw Rd, Bataw, Meghalaya 793150, India",
      "addressComponents": [
        {
          "longText": "66HW+JFJ",
          "shortText": "66HW+JFJ",
          "types": [
            "plus_code"
          ],
          "languageCode": "en-US"
        },
        {
          "longText": "Bataw Road",
          "shortText": "Bataw Rd",
          "types": [
            "route"
          ],
          "languageCode": "en"
        },
        {
          "longText": "Bataw",
          "shortText": "Bataw",
          "types": [
            "locality",
            "political"
          ],
          "languageCode": "en"
        },
        {
          "longText": "East Jaintia Hills",
          "shortText": "East Jaintia Hills",
          "types": [
            "administrative_area_level_3",
            "political"
          ],
          "languageCode": "en"
        },
        {
          "longText": "Shillong Division",
          "shortText": "Shillong Division",
          "types": [
            "administrative_area_level_2",
            "political"
          ],
          "languageCode": "en"
        },
        {
          "longText": "Meghalaya",
          "shortText": "ML",
          "types": [
            "administrative_area_level_1",
            "political"
          ],
          "languageCode": "en"
        },
        {
          "longText": "India",
          "shortText": "IN",
          "types": [
            "country",
            "political"
          ],
          "languageCode": "en"
        },
        {
          "longText": "793150",
          "shortText": "793150",
          "types": [
            "postal_code"
          ],
          "languageCode": "en-US"
        }
      ],
      "location": {
        "latitude": 25.2290976,
        "longitude": 92.2461392
      },
      "viewport": {
        "low": {
          "latitude": 25.227738319708497,
          "longitude": 92.2447446697085
        },
        "high": {
          "latitude": 25.2304362802915,
          "longitude": 92.2474426302915
        }
      },
      "googleMapsUri": "https://maps.google.com/?cid=14019557177610406097",
      "utcOffsetMinutes": 330,
      "adrFormatAddress": "66HW+JFJ, \u003cspan class=\"street-address\"\u003eBataw Rd\u003c/span\u003e, \u003cspan class=\"locality\"\u003eBataw\u003c/span\u003e, \u003cspan class=\"region\"\u003eMeghalaya\u003c/span\u003e \u003cspan class=\"postal-code\"\u003e793150\u003c/span\u003e, \u003cspan class=\"country-name\"\u003eIndia\u003c/span\u003e",
      "businessStatus": "OPERATIONAL",
      "iconMaskBaseUri": "https://maps.gstatic.com/mapfiles/place_api/icons/v2/worship_christian_pinlet",
      "iconBackgroundColor": "#7B9EB0",
      "displayName": {
        "text": "Bataw Presbyterian Church",
        "languageCode": "en"
      },
      "primaryTypeDisplayName": {
        "text": "Church",
        "languageCode": "en-US"
      },
      "primaryType": "church",
      "shortFormattedAddress": "66HW+JFJ, Bataw Rd, Bataw",
      "photos": [
        {
          "name": "places/ChIJcxmz41Y9UDcR0Qi_Z_l4j8I/photos/ATplDJaRHpIjMZqlgTbGUgaxXKvrkumWNfV9v_qpgeps6jGnJJAjBYh8LBioz-YKrpZka8fiY6fgMCrLIY3Na-Z9OoFsmpayAvb1hH23NLks4d12syyyTs0tUumwuSuS8FQ1y3RNf7BjPTuXVrWnp1fCnUujYt7xofMCC9CV",
          "widthPx": 4608,
          "heightPx": 3456,
          "authorAttributions": [
            {
              "displayName": "DONSHANSKHEMTHABAH Thabah",
              "uri": "//maps.google.com/maps/contrib/105855195725145416466",
              "photoUri": "//lh3.googleusercontent.com/a-/ALV-UjWBi1pZO0HINdLYcqpgDCfuBnO3KEkpnqsL2FW42pmwmyOzz0MA=s100-p-k-no-mo"
            }
          ]
        },
        {
          "name": "places/ChIJcxmz41Y9UDcR0Qi_Z_l4j8I/photos/ATplDJblZs6coKC6cVZzmp-FtYwnOYIetj1Ot63Fv0uEuKCKf0zkJA_0znVYoN0-EcdS07htOxLUfcrq0_NKnJry_L6cpDsMVECmu3tLiSCeMGl-R8mCeNlEe5h0Phv2Tbp4cM8HtV3aibnqaZeo5oltQ92Y-f7vST1i7csi",
          "widthPx": 5760,
          "heightPx": 4320,
          "authorAttributions": [
            {
              "displayName": "DONSHANSKHEMTHABAH Thabah",
              "uri": "//maps.google.com/maps/contrib/105855195725145416466",
              "photoUri": "//lh3.googleusercontent.com/a-/ALV-UjWBi1pZO0HINdLYcqpgDCfuBnO3KEkpnqsL2FW42pmwmyOzz0MA=s100-p-k-no-mo"
            }
          ]
        },
        {
          "name": "places/ChIJcxmz41Y9UDcR0Qi_Z_l4j8I/photos/ATplDJYiAGJYZ5Pcb_ut6uCNhhSmaUxIlWmR33fTfBI9Isf44LeOzWDfAmpcgWXMflylYCsQRIxYDNd12cA9SYD8jlYmADSs824HBny862GIYsxFAuuw7CsK7qS5KQH0jr5UVtj4wBE_OF-i2AizKameQ1RHx2_YsBWtILSH",
          "widthPx": 4608,
          "heightPx": 3456,
          "authorAttributions": [
            {
              "displayName": "DONSHANSKHEMTHABAH Thabah",
              "uri": "//maps.google.com/maps/contrib/105855195725145416466",
              "photoUri": "//lh3.googleusercontent.com/a-/ALV-UjWBi1pZO0HINdLYcqpgDCfuBnO3KEkpnqsL2FW42pmwmyOzz0MA=s100-p-k-no-mo"
            }
          ]
        },
        {
          "name": "places/ChIJcxmz41Y9UDcR0Qi_Z_l4j8I/photos/ATplDJZgaKc1pGPYjRLF5NIeCaPh9M8JcuZinz7_mRooefgCUm9AnlPN9BTvPOCucca8dwF3dEz7xtm0GEQa8T2A23XBD-pbDCutTNmhWhRtgpgGupxvTDM2Fsfwij6TACC9JR7K3-W86WiHsU5IvaPfzeqd6aEvbwYH20zW",
          "widthPx": 5760,
          "heightPx": 2736,
          "authorAttributions": [
            {
              "displayName": "DONSHANSKHEMTHABAH Thabah",
              "uri": "//maps.google.com/maps/contrib/105855195725145416466",
              "photoUri": "//lh3.googleusercontent.com/a-/ALV-UjWBi1pZO0HINdLYcqpgDCfuBnO3KEkpnqsL2FW42pmwmyOzz0MA=s100-p-k-no-mo"
            }
          ]
        },
        {
          "name": "places/ChIJcxmz41Y9UDcR0Qi_Z_l4j8I/photos/ATplDJaMgxEpXv0sph1Vs4OiKm-iJAd3gHMrN8SLl9VV_CyFC6XtZFPxpigMw5NOiU7YOoTAC-jf8xNniY13P7bMHF7AwfuV8z9J344G9_u-xJLO44npkNJlvjNr9NuR0u6t4fsnTg5OMWiETLs4TrXbRKY-StAVSNvivcpI",
          "widthPx": 4608,
          "heightPx": 3456,
          "authorAttributions": [
            {
              "displayName": "DONSHANSKHEMTHABAH Thabah",
              "uri": "//maps.google.com/maps/contrib/105855195725145416466",
              "photoUri": "//lh3.googleusercontent.com/a-/ALV-UjWBi1pZO0HINdLYcqpgDCfuBnO3KEkpnqsL2FW42pmwmyOzz0MA=s100-p-k-no-mo"
            }
          ]
        },
        {
          "name": "places/ChIJcxmz41Y9UDcR0Qi_Z_l4j8I/photos/ATplDJbXBtNXPnoEbc3tOURR1Zlg4q_XvTQ8omHsULUMcGZ9yt9W-LO2U-meN2JWif4UsvTqv3UaQ6RlaisANQ89FQi3kuTS_P23q8KU-5idShJstI3RszoO9VNLHvVr-oNTn5E-YxqAsBVv1ajES_IZxqBZhdukpc4keo_h",
          "widthPx": 4560,
          "heightPx": 2160,
          "authorAttributions": [
            {
              "displayName": "DONSHANSKHEMTHABAH Thabah",
              "uri": "//maps.google.com/maps/contrib/105855195725145416466",
              "photoUri": "//lh3.googleusercontent.com/a-/ALV-UjWBi1pZO0HINdLYcqpgDCfuBnO3KEkpnqsL2FW42pmwmyOzz0MA=s100-p-k-no-mo"
            }
          ]
        }
      ]
    },
    {
      "name": "places/ChIJE1B0FV49UDcRm_74oUcCZqk",
      "id": "ChIJE1B0FV49UDcRm_74oUcCZqk",
      "types": [
        "church",
        "place_of_worship",
        "point_of_interest",
        "establishment"
      ],
      "formattedAddress": "57W4+895, Ladlakadong, Meghalaya 793150, India",
      "addressComponents": [
        {
          "longText": "57W4+895",
          "shortText": "57W4+895",
          "types": [
            "plus_code"
          ],
          "languageCode": "en-US"
        },
        {
          "longText": "Ladlakadong",
          "shortText": "Ladlakadong",
          "types": [
            "locality",
            "political"
          ],
          "languageCode": "en"
        },
        {
          "longText": "East Jaintia Hills",
          "shortText": "East Jaintia Hills",
          "types": [
            "administrative_area_level_3",
            "political"
          ],
          "languageCode": "en"
        },
        {
          "longText": "Shillong Division",
          "shortText": "Shillong Division",
          "types": [
            "administrative_area_level_2",
            "political"
          ],
          "languageCode": "en"
        },
        {
          "longText": "Meghalaya",
          "shortText": "ML",
          "types": [
            "administrative_area_level_1",
            "political"
          ],
          "languageCode": "en"
        },
        {
          "longText": "India",
          "shortText": "IN",
          "types": [
            "country",
            "political"
          ],
          "languageCode": "en"
        },
        {
          "longText": "793150",
          "shortText": "793150",
          "types": [
            "postal_code"
          ],
          "languageCode": "en-US"
        }
      ],
      "location": {
        "latitude": 25.195766799999998,
        "longitude": 92.2559902
      },
      "viewport": {
        "low": {
          "latitude": 25.194484969708498,
          "longitude": 92.254678369708486
        },
        "high": {
          "latitude": 25.197182930291504,
          "longitude": 92.257376330291493
        }
      },
      "googleMapsUri": "https://maps.google.com/?cid=12206446346717691547",
      "utcOffsetMinutes": 330,
      "adrFormatAddress": "57W4+895, \u003cspan class=\"locality\"\u003eLadlakadong\u003c/span\u003e, \u003cspan class=\"region\"\u003eMeghalaya\u003c/span\u003e \u003cspan class=\"postal-code\"\u003e793150\u003c/span\u003e, \u003cspan class=\"country-name\"\u003eIndia\u003c/span\u003e",
      "businessStatus": "OPERATIONAL",
      "iconMaskBaseUri": "https://maps.gstatic.com/mapfiles/place_api/icons/v2/worship_christian_pinlet",
      "iconBackgroundColor": "#7B9EB0",
      "displayName": {
        "text": "St.Eugene Parish, Ladlakadong",
        "languageCode": "en"
      },
      "primaryTypeDisplayName": {
        "text": "Church",
        "languageCode": "en-US"
      },
      "primaryType": "church",
      "shortFormattedAddress": "57W4+895, Ladlakadong"
    },
    {
      "name": "places/ChIJjQGduqI9UDcRjSrEVKYxYRM",
      "id": "ChIJjQGduqI9UDcRjSrEVKYxYRM",
      "types": [
        "church",
        "place_of_worship",
        "point_of_interest",
        "establishment"
      ],
      "formattedAddress": "57WH+W34, Umlatdoh, Meghalaya 793150, India",
      "addressComponents": [
        {
          "longText": "57WH+W34",
          "shortText": "57WH+W34",
          "types": [
            "plus_code"
          ],
          "languageCode": "en-US"
        },
        {
          "longText": "Umlatdoh",
          "shortText": "Umlatdoh",
          "types": [
            "locality",
            "political"
          ],
          "languageCode": "en"
        },
        {
          "longText": "East Jaintia Hills",
          "shortText": "East Jaintia Hills",
          "types": [
            "administrative_area_level_3",
            "political"
          ],
          "languageCode": "en"
        },
        {
          "longText": "Shillong Division",
          "shortText": "Shillong Division",
          "types": [
            "administrative_area_level_2",
            "political"
          ],
          "languageCode": "en"
        },
        {
          "longText": "Meghalaya",
          "shortText": "ML",
          "types": [
            "administrative_area_level_1",
            "political"
          ],
          "languageCode": "en"
        },
        {
          "longText": "India",
          "shortText": "IN",
          "types": [
            "country",
            "political"
          ],
          "languageCode": "en"
        },
        {
          "longText": "793150",
          "shortText": "793150",
          "types": [
            "postal_code"
          ],
          "languageCode": "en-US"
        }
      ],
      "location": {
        "latitude": 25.197265700000003,
        "longitude": 92.27771709999999
      },
      "viewport": {
        "low": {
          "latitude": 25.195881519708497,
          "longitude": 92.276316219708491
        },
        "high": {
          "latitude": 25.198579480291503,
          "longitude": 92.2790141802915
        }
      },
      "rating": 5,
      "googleMapsUri": "https://maps.google.com/?cid=1396451949918038669",
      "utcOffsetMinutes": 330,
      "adrFormatAddress": "57WH+W34, \u003cspan class=\"locality\"\u003eUmlatdoh\u003c/span\u003e, \u003cspan class=\"region\"\u003eMeghalaya\u003c/span\u003e \u003cspan class=\"postal-code\"\u003e793150\u003c/span\u003e, \u003cspan class=\"country-name\"\u003eIndia\u003c/span\u003e",
      "businessStatus": "OPERATIONAL",
      "userRatingCount": 2,
      "iconMaskBaseUri": "https://maps.gstatic.com/mapfiles/place_api/icons/v2/worship_christian_pinlet",
      "iconBackgroundColor": "#7B9EB0",
      "displayName": {
        "text": "Lakadong Presbyterian Church",
        "languageCode": "en"
      },
      "primaryTypeDisplayName": {
        "text": "Church",
        "languageCode": "en-US"
      },
      "primaryType": "church",
      "shortFormattedAddress": "57WH+W34, Umlatdoh",
      "reviews": [
        {
          "name": "places/ChIJjQGduqI9UDcRjSrEVKYxYRM/reviews/ChdDSUhNMG9nS0VJQ0FnSUNKMXFpd3NRRRAB",
          "relativePublishTimeDescription": "10 months ago",
          "rating": 5,
          "authorAttribution": {
            "displayName": "Pynshaitbor Shadong",
            "uri": "https://www.google.com/maps/contrib/115530270693675873741/reviews",
            "photoUri": "https://lh3.googleusercontent.com/a/ACg8ocLNIBEnC2cEASy1RO6PfAmggwOVo-LdeNmtpt-pEJLbs3Ww-T2u=s128-c0x00000000-cc-rp-mo"
          },
          "publishTime": "2023-06-26T17:35:50Z"
        },
        {
          "name": "places/ChIJjQGduqI9UDcRjSrEVKYxYRM/reviews/ChdDSUhNMG9nS0VJQ0FnSUNCd191T3BRRRAB",
          "relativePublishTimeDescription": "a year ago",
          "rating": 5,
          "authorAttribution": {
            "displayName": "Hameuri Rabon",
            "uri": "https://www.google.com/maps/contrib/104670534160200965932/reviews",
            "photoUri": "https://lh3.googleusercontent.com/a/ACg8ocKAaz81ysEFl-Yu5vmMDo-Oqib94dNERv4qKytsicW6B98txg=s128-c0x00000000-cc-rp-mo"
          },
          "publishTime": "2023-01-03T05:15:45Z"
        }
      ],
      "photos": [
        {
          "name": "places/ChIJjQGduqI9UDcRjSrEVKYxYRM/photos/ATplDJbkviBVFbbjNTjpu9_DL3phoepf_iADronDXH4Z0fDauZplkWBjOSw_BAlOrcWn_paiVPcmCwiR6Th5Qj6ttFQ3q_wYusiCAIpxHKO_4crD56XKYk392Ns4OAN0ByEybFtO10LiNorD8r_k3CZTReZ5XnR_K-89jqfm",
          "widthPx": 5163,
          "heightPx": 3872,
          "authorAttributions": [
            {
              "displayName": "Hameuri Rabon",
              "uri": "//maps.google.com/maps/contrib/104670534160200965932",
              "photoUri": "//lh3.googleusercontent.com/a/ACg8ocKAaz81ysEFl-Yu5vmMDo-Oqib94dNERv4qKytsicW6B98txg=s100-p-k-no-mo"
            }
          ]
        },
        {
          "name": "places/ChIJjQGduqI9UDcRjSrEVKYxYRM/photos/ATplDJZx4m0UENCslIXaAMt1xxmQBLo5WlBAXPmGtG-qxr-vyan3OEwxUGI5kb-x4jJiSEoG9Wzbx1S0U7oUt4DC0Y7zWASBJdWqD2_Zt3kR-8brYHx92R5DChpVv0_aw2m5xQEoDL8J00CYU7YKQ4bLWubMp15l1nUa-n3l",
          "widthPx": 2160,
          "heightPx": 1619,
          "authorAttributions": [
            {
              "displayName": "Hameuri Rabon",
              "uri": "//maps.google.com/maps/contrib/104670534160200965932",
              "photoUri": "//lh3.googleusercontent.com/a/ACg8ocKAaz81ysEFl-Yu5vmMDo-Oqib94dNERv4qKytsicW6B98txg=s100-p-k-no-mo"
            }
          ]
        },
        {
          "name": "places/ChIJjQGduqI9UDcRjSrEVKYxYRM/photos/ATplDJaRiRv6XApJSLZ7xlgC5igILAKroGda1l-93T30bW0gjOlOTfWhpZoIhaWwfitFmRD8cJy-YDwig-MF01UDYzF24BENcbWh1d6Vs30CR0usU0eXSe9qe1edx-izjSB_NDuojXiXZeJD_1YBCzX8GSrrysMNhjjyRtYh",
          "widthPx": 3000,
          "heightPx": 4000,
          "authorAttributions": [
            {
              "displayName": "Pynshaitbor Shadong",
              "uri": "//maps.google.com/maps/contrib/115530270693675873741",
              "photoUri": "//lh3.googleusercontent.com/a/ACg8ocLNIBEnC2cEASy1RO6PfAmggwOVo-LdeNmtpt-pEJLbs3Ww-T2u=s100-p-k-no-mo"
            }
          ]
        },
        {
          "name": "places/ChIJjQGduqI9UDcRjSrEVKYxYRM/photos/ATplDJYNO8ea0wYhSnunTSRdy_3FUrPj5FchalhAx3pJqWtrUrCXHC2Iq4AWud-zFPfombAr-S4x98uK6jASnfijNOHcuNaSoRUEHHPqrffc61S4rJzp9PIUTVgIE2liXaGGqG5_ykuOo62HEC8rnL5ZsaDa7nrDhdPqO065",
          "widthPx": 3264,
          "heightPx": 1472,
          "authorAttributions": [
            {
              "displayName": "Hameuri Rabon",
              "uri": "//maps.google.com/maps/contrib/104670534160200965932",
              "photoUri": "//lh3.googleusercontent.com/a/ACg8ocKAaz81ysEFl-Yu5vmMDo-Oqib94dNERv4qKytsicW6B98txg=s100-p-k-no-mo"
            }
          ]
        },
        {
          "name": "places/ChIJjQGduqI9UDcRjSrEVKYxYRM/photos/ATplDJYXcHW4GjgIyvB4hn64oJWpmbs-goXl4kbkjJiqIENaqp5XxKcGOJFuPJi-7hFrHLqRNgVL_763lIJfvF0QNnRd20yW4NXZUFdCAF8rTZMTsX_4fWqjUQgStPBpLQEbGIGwGKvIdJ2o2h8MHq-E2IzjueAJqJbq_gQ3",
          "widthPx": 4160,
          "heightPx": 3120,
          "authorAttributions": [
            {
              "displayName": "Bran Amkhloo",
              "uri": "//maps.google.com/maps/contrib/113027854476883861261",
              "photoUri": "//lh3.googleusercontent.com/a/ACg8ocKgOC38py1o1f1E1cWS3_mwu4UUUvIXWuNxlT6J55vzH-YkSQ=s100-p-k-no-mo"
            }
          ]
        }
      ]
    },
    {
      "name": "places/ChIJ5ckylMI9UDcRfjE6TEjgFks",
      "id": "ChIJ5ckylMI9UDcRfjE6TEjgFks",
      "types": [
        "tourist_attraction",
        "point_of_interest",
        "establishment"
      ],
      "formattedAddress": "66PH+473, Bataw, Meghalaya 793150, India",
      "addressComponents": [
        {
          "longText": "66PH+473",
          "shortText": "66PH+473",
          "types": [
            "plus_code"
          ],
          "languageCode": "en-US"
        },
        {
          "longText": "Bataw",
          "shortText": "Bataw",
          "types": [
            "locality",
            "political"
          ],
          "languageCode": "en"
        },
        {
          "longText": "East Jaintia Hills",
          "shortText": "East Jaintia Hills",
          "types": [
            "administrative_area_level_3",
            "political"
          ],
          "languageCode": "en"
        },
        {
          "longText": "Shillong Division",
          "shortText": "Shillong Division",
          "types": [
            "administrative_area_level_2",
            "political"
          ],
          "languageCode": "en"
        },
        {
          "longText": "Meghalaya",
          "shortText": "ML",
          "types": [
            "administrative_area_level_1",
            "political"
          ],
          "languageCode": "en"
        },
        {
          "longText": "India",
          "shortText": "IN",
          "types": [
            "country",
            "political"
          ],
          "languageCode": "en"
        },
        {
          "longText": "793150",
          "shortText": "793150",
          "types": [
            "postal_code"
          ],
          "languageCode": "en-US"
        }
      ],
      "location": {
        "latitude": 25.2352742,
        "longitude": 92.22818
      },
      "viewport": {
        "low": {
          "latitude": 25.233925219708496,
          "longitude": 92.226831019708484
        },
        "high": {
          "latitude": 25.236623180291502,
          "longitude": 92.2295289802915
        }
      },
      "googleMapsUri": "https://maps.google.com/?cid=5410758603453378942",
      "utcOffsetMinutes": 330,
      "adrFormatAddress": "66PH+473, \u003cspan class=\"locality\"\u003eBataw\u003c/span\u003e, \u003cspan class=\"region\"\u003eMeghalaya\u003c/span\u003e \u003cspan class=\"postal-code\"\u003e793150\u003c/span\u003e, \u003cspan class=\"country-name\"\u003eIndia\u003c/span\u003e",
      "businessStatus": "CLOSED_TEMPORARILY",
      "iconMaskBaseUri": "https://maps.gstatic.com/mapfiles/place_api/icons/v2/generic_pinlet",
      "iconBackgroundColor": "#13B5C7",
      "displayName": {
        "text": "Power House",
        "languageCode": "en"
      },
      "primaryTypeDisplayName": {
        "text": "Tourist Attraction",
        "languageCode": "en-US"
      },
      "primaryType": "tourist_attraction",
      "shortFormattedAddress": "66PH+473, Bataw"
    },
    {
      "name": "places/ChIJuecltIw9UDcRK5he4UJhtso",
      "id": "ChIJuecltIw9UDcRK5he4UJhtso",
      "types": [
        "church",
        "place_of_worship",
        "point_of_interest",
        "establishment"
      ],
      "formattedAddress": "66JV+HP6, near Umhang, Bataw, Meghalaya 793150, India",
      "addressComponents": [
        {
          "longText": "66JV+HP6",
          "shortText": "66JV+HP6",
          "types": [
            "plus_code"
          ],
          "languageCode": "en-US"
        },
        {
          "longText": "Umhang",
          "shortText": "Umhang",
          "types": [
            "landmark"
          ],
          "languageCode": "en"
        },
        {
          "longText": "Bataw",
          "shortText": "Bataw",
          "types": [
            "locality",
            "political"
          ],
          "languageCode": "en"
        },
        {
          "longText": "East Jaintia Hills",
          "shortText": "East Jaintia Hills",
          "types": [
            "administrative_area_level_3",
            "political"
          ],
          "languageCode": "en"
        },
        {
          "longText": "Shillong Division",
          "shortText": "Shillong Division",
          "types": [
            "administrative_area_level_2",
            "political"
          ],
          "languageCode": "en"
        },
        {
          "longText": "Meghalaya",
          "shortText": "ML",
          "types": [
            "administrative_area_level_1",
            "political"
          ],
          "languageCode": "en"
        },
        {
          "longText": "India",
          "shortText": "IN",
          "types": [
            "country",
            "political"
          ],
          "languageCode": "en"
        },
        {
          "longText": "793150",
          "shortText": "793150",
          "types": [
            "postal_code"
          ],
          "languageCode": "en-US"
        }
      ],
      "location": {
        "latitude": 25.2314044,
        "longitude": 92.24425509999999
      },
      "viewport": {
        "low": {
          "latitude": 25.230064019708497,
          "longitude": 92.242945069708483
        },
        "high": {
          "latitude": 25.232761980291503,
          "longitude": 92.2456430302915
        }
      },
      "googleMapsUri": "https://maps.google.com/?cid=14606969381299591211",
      "utcOffsetMinutes": 330,
      "adrFormatAddress": "66JV+HP6, near Umhang, \u003cspan class=\"locality\"\u003eBataw\u003c/span\u003e, \u003cspan class=\"region\"\u003eMeghalaya\u003c/span\u003e \u003cspan class=\"postal-code\"\u003e793150\u003c/span\u003e, \u003cspan class=\"country-name\"\u003eIndia\u003c/span\u003e",
      "businessStatus": "OPERATIONAL",
      "iconMaskBaseUri": "https://maps.gstatic.com/mapfiles/place_api/icons/v2/worship_christian_pinlet",
      "iconBackgroundColor": "#7B9EB0",
      "displayName": {
        "text": "Church Of God (M&A), Bataw",
        "languageCode": "en"
      },
      "primaryTypeDisplayName": {
        "text": "Church",
        "languageCode": "en-US"
      },
      "primaryType": "church",
      "shortFormattedAddress": "66JV+HP6, Umhang, Bataw",
      "photos": [
        {
          "name": "places/ChIJuecltIw9UDcRK5he4UJhtso/photos/ATplDJaoB4AM7lSjnxucNnhJ2AFmAhIz84PDzOswOoAGpDHP-PPVN2oh8O-z9vphj2ocwIH5euWBjUqV-_WBvM2OBX_baPWyoI01CsRYR7p3gueQ5v4spl-Gu5YSnOigU61ypPHPW1IzXP4CTl0YIOmnSaN02w69IUklX-3F",
          "widthPx": 4560,
          "heightPx": 2160,
          "authorAttributions": [
            {
              "displayName": "DONSHANSKHEMTHABAH Thabah",
              "uri": "//maps.google.com/maps/contrib/105855195725145416466",
              "photoUri": "//lh3.googleusercontent.com/a-/ALV-UjWBi1pZO0HINdLYcqpgDCfuBnO3KEkpnqsL2FW42pmwmyOzz0MA=s100-p-k-no-mo"
            }
          ]
        }
      ]
    },
    {
      "name": "places/ChIJvT5mM3o_UDcRj1dXYGvAIfY",
      "id": "ChIJvT5mM3o_UDcRj1dXYGvAIfY",
      "types": [
        "historical_landmark",
        "point_of_interest",
        "establishment"
      ],
      "formattedAddress": "6695+876, Satpator, Meghalaya 793150, India",
      "addressComponents": [
        {
          "longText": "6695+876",
          "shortText": "6695+876",
          "types": [
            "plus_code"
          ],
          "languageCode": "en-US"
        },
        {
          "longText": "Satpator",
          "shortText": "Satpator",
          "types": [
            "locality",
            "political"
          ],
          "languageCode": "en"
        },
        {
          "longText": "West Jaintia Hills",
          "shortText": "West Jaintia Hills",
          "types": [
            "administrative_area_level_3",
            "political"
          ],
          "languageCode": "en"
        },
        {
          "longText": "Shillong Division",
          "shortText": "Shillong Division",
          "types": [
            "administrative_area_level_2",
            "political"
          ],
          "languageCode": "en"
        },
        {
          "longText": "Meghalaya",
          "shortText": "ML",
          "types": [
            "administrative_area_level_1",
            "political"
          ],
          "languageCode": "en"
        },
        {
          "longText": "India",
          "shortText": "IN",
          "types": [
            "country",
            "political"
          ],
          "languageCode": "en"
        },
        {
          "longText": "793150",
          "shortText": "793150",
          "types": [
            "postal_code"
          ],
          "languageCode": "en-US"
        }
      ],
      "location": {
        "latitude": 25.218297399999997,
        "longitude": 92.208136599999989
      },
      "viewport": {
        "low": {
          "latitude": 25.216881219708494,
          "longitude": 92.2070506197085
        },
        "high": {
          "latitude": 25.2195791802915,
          "longitude": 92.209748580291517
        }
      },
      "rating": 2.5,
      "googleMapsUri": "https://maps.google.com/?cid=17735668374972094351",
      "utcOffsetMinutes": 330,
      "adrFormatAddress": "6695+876, \u003cspan class=\"locality\"\u003eSatpator\u003c/span\u003e, \u003cspan class=\"region\"\u003eMeghalaya\u003c/span\u003e \u003cspan class=\"postal-code\"\u003e793150\u003c/span\u003e, \u003cspan class=\"country-name\"\u003eIndia\u003c/span\u003e",
      "businessStatus": "OPERATIONAL",
      "userRatingCount": 2,
      "iconMaskBaseUri": "https://maps.gstatic.com/mapfiles/place_api/icons/v2/generic_pinlet",
      "iconBackgroundColor": "#13B5C7",
      "displayName": {
        "text": "Chrei sme ksiang",
        "languageCode": "en"
      },
      "primaryTypeDisplayName": {
        "text": "Historical Landmark",
        "languageCode": "en-US"
      },
      "primaryType": "historical_landmark",
      "shortFormattedAddress": "6695+876, Satpator",
      "reviews": [
        {
          "name": "places/ChIJvT5mM3o_UDcRj1dXYGvAIfY/reviews/ChdDSUhNMG9nS0VJQ0FnSURWdEtDNW1nRRAB",
          "relativePublishTimeDescription": "4 months ago",
          "rating": 1,
          "text": {
            "text": "Chisil N Sangma",
            "languageCode": "en-US"
          },
          "originalText": {
            "text": "Chisil N Sangma",
            "languageCode": "zh"
          },
          "authorAttribution": {
            "displayName": "Chisil Sangma",
            "uri": "https://www.google.com/maps/contrib/109817635494285045347/reviews",
            "photoUri": "https://lh3.googleusercontent.com/a/ACg8ocJTVWVjJJQmYjQ9oAwXNhODvf0qV1gnd_PJOaDpuj-NGkRhIQ=s128-c0x00000000-cc-rp-mo"
          },
          "publishTime": "2023-12-11T07:22:35Z"
        },
        {
          "name": "places/ChIJvT5mM3o_UDcRj1dXYGvAIfY/reviews/ChZDSUhNMG9nS0VJQ0FnSUNwdS0ycEFnEAE",
          "relativePublishTimeDescription": "8 months ago",
          "rating": 4,
          "authorAttribution": {
            "displayName": "nam D",
            "uri": "https://www.google.com/maps/contrib/108777875174563174838/reviews",
            "photoUri": "https://lh3.googleusercontent.com/a-/ALV-UjVIz8jboJ3QggAmTKQjhyrbk3vBKWqn-XKWEmIxGVohw_r_pdLk=s128-c0x00000000-cc-rp-mo"
          },
          "publishTime": "2023-08-11T08:18:53Z"
        }
      ],
      "photos": [
        {
          "name": "places/ChIJvT5mM3o_UDcRj1dXYGvAIfY/photos/ATplDJZPnTNzVPbVTptJTeKAtNUUMiJFTCu08MnbQ9Ws51X61pE6JhZvXIbdZXqEo9pr0iJxj2JNwWAryv36pEo1laDo-UdpREYOGoML5P254vLqMWvqo6KbyevGrbGWeHentQzyZgjFjgUWGjLCZKbjAXoierzPJYG0vLBx",
          "widthPx": 2448,
          "heightPx": 3264,
          "authorAttributions": [
            {
              "displayName": "nam D",
              "uri": "//maps.google.com/maps/contrib/108777875174563174838",
              "photoUri": "//lh3.googleusercontent.com/a-/ALV-UjVIz8jboJ3QggAmTKQjhyrbk3vBKWqn-XKWEmIxGVohw_r_pdLk=s100-p-k-no-mo"
            }
          ]
        },
        {
          "name": "places/ChIJvT5mM3o_UDcRj1dXYGvAIfY/photos/ATplDJbTHFJRRBt-dX58tW9MicRsL1OM3lslSae1xY_J0qoQ10zdhyMusaahkhpe_eQ6OWKEdQG_JWyZ7JWFMNvTC-z0iLVdFqGLNPb8VP2H8Y2-XUEmdHdqaF_ndKtDzE2d379FWpR1QIu1JT3IWfKsff-Ux_1TC6OM_20K",
          "widthPx": 715,
          "heightPx": 719,
          "authorAttributions": [
            {
              "displayName": "Chisil Sangma",
              "uri": "//maps.google.com/maps/contrib/109817635494285045347",
              "photoUri": "//lh3.googleusercontent.com/a/ACg8ocJTVWVjJJQmYjQ9oAwXNhODvf0qV1gnd_PJOaDpuj-NGkRhIQ=s100-p-k-no-mo"
            }
          ]
        }
      ],
      "goodForChildren": true
    },
    {
      "name": "places/ChIJ3-Uj24M9UDcRjnpRQmsqvCA",
      "id": "ChIJ3-Uj24M9UDcRjnpRQmsqvCA",
      "types": [
        "tourist_attraction",
        "point_of_interest",
        "establishment"
      ],
      "formattedAddress": "768Q+P6, Suchen Dhana, Meghalaya 793150, India",
      "addressComponents": [
        {
          "longText": "768Q+P6",
          "shortText": "768Q+P6",
          "types": [
            "plus_code"
          ],
          "languageCode": "en-US"
        },
        {
          "longText": "Suchen Dhana",
          "shortText": "Suchen Dhana",
          "types": [
            "locality",
            "political"
          ],
          "languageCode": "en"
        },
        {
          "longText": "East Jaintia Hills",
          "shortText": "East Jaintia Hills",
          "types": [
            "administrative_area_level_3",
            "political"
          ],
          "languageCode": "en"
        },
        {
          "longText": "Shillong Division",
          "shortText": "Shillong Division",
          "types": [
            "administrative_area_level_2",
            "political"
          ],
          "languageCode": "en"
        },
        {
          "longText": "Meghalaya",
          "shortText": "ML",
          "types": [
            "administrative_area_level_1",
            "political"
          ],
          "languageCode": "en"
        },
        {
          "longText": "India",
          "shortText": "IN",
          "types": [
            "country",
            "political"
          ],
          "languageCode": "en"
        },
        {
          "longText": "793150",
          "shortText": "793150",
          "types": [
            "postal_code"
          ],
          "languageCode": "en-US"
        }
      ],
      "location": {
        "latitude": 25.266776399999998,
        "longitude": 92.2381133
      },
      "viewport": {
        "low": {
          "latitude": 25.265427419708494,
          "longitude": 92.2367643197085
        },
        "high": {
          "latitude": 25.2681253802915,
          "longitude": 92.2394622802915
        }
      },
      "googleMapsUri": "https://maps.google.com/?cid=2358806944997800590",
      "utcOffsetMinutes": 330,
      "adrFormatAddress": "768Q+P6, \u003cspan class=\"locality\"\u003eSuchen Dhana\u003c/span\u003e, \u003cspan class=\"region\"\u003eMeghalaya\u003c/span\u003e \u003cspan class=\"postal-code\"\u003e793150\u003c/span\u003e, \u003cspan class=\"country-name\"\u003eIndia\u003c/span\u003e",
      "businessStatus": "CLOSED_TEMPORARILY",
      "iconMaskBaseUri": "https://maps.gstatic.com/mapfiles/place_api/icons/v2/generic_pinlet",
      "iconBackgroundColor": "#13B5C7",
      "displayName": {
        "text": "Synrang Umkram",
        "languageCode": "en"
      },
      "primaryTypeDisplayName": {
        "text": "Tourist Attraction",
        "languageCode": "en-US"
      },
      "primaryType": "tourist_attraction",
      "shortFormattedAddress": "768Q+P6, Suchen Dhana"
    },
    {
      "name": "places/ChIJ5XHMFgA_UDcR5BhL0jON9JY",
      "id": "ChIJ5XHMFgA_UDcR5BhL0jON9JY",
      "types": [
        "church",
        "place_of_worship",
        "point_of_interest",
        "establishment"
      ],
      "formattedAddress": "768F+J7C, Suchen Mulieh, Meghalaya 793150, India",
      "addressComponents": [
        {
          "longText": "768F+J7C",
          "shortText": "768F+J7C",
          "types": [
            "plus_code"
          ],
          "languageCode": "en-US"
        },
        {
          "longText": "Suchen Mulieh",
          "shortText": "Suchen Mulieh",
          "types": [
            "locality",
            "political"
          ],
          "languageCode": "en"
        },
        {
          "longText": "East Jaintia Hills",
          "shortText": "East Jaintia Hills",
          "types": [
            "administrative_area_level_3",
            "political"
          ],
          "languageCode": "en"
        },
        {
          "longText": "Shillong Division",
          "shortText": "Shillong Division",
          "types": [
            "administrative_area_level_2",
            "political"
          ],
          "languageCode": "en"
        },
        {
          "longText": "Meghalaya",
          "shortText": "ML",
          "types": [
            "administrative_area_level_1",
            "political"
          ],
          "languageCode": "en"
        },
        {
          "longText": "India",
          "shortText": "IN",
          "types": [
            "country",
            "political"
          ],
          "languageCode": "en"
        },
        {
          "longText": "793150",
          "shortText": "793150",
          "types": [
            "postal_code"
          ],
          "languageCode": "en-US"
        }
      ],
      "location": {
        "latitude": 25.266565,
        "longitude": 92.223146700000015
      },
      "viewport": {
        "low": {
          "latitude": 25.265501569708498,
          "longitude": 92.2218135197085
        },
        "high": {
          "latitude": 25.268199530291504,
          "longitude": 92.224511480291511
        }
      },
      "googleMapsUri": "https://maps.google.com/?cid=10877474253717575908",
      "utcOffsetMinutes": 330,
      "adrFormatAddress": "768F+J7C, \u003cspan class=\"locality\"\u003eSuchen Mulieh\u003c/span\u003e, \u003cspan class=\"region\"\u003eMeghalaya\u003c/span\u003e \u003cspan class=\"postal-code\"\u003e793150\u003c/span\u003e, \u003cspan class=\"country-name\"\u003eIndia\u003c/span\u003e",
      "businessStatus": "OPERATIONAL",
      "iconMaskBaseUri": "https://maps.gstatic.com/mapfiles/place_api/icons/v2/worship_christian_pinlet",
      "iconBackgroundColor": "#7B9EB0",
      "displayName": {
        "text": "Suchen mulieh",
        "languageCode": "en"
      },
      "primaryTypeDisplayName": {
        "text": "Church",
        "languageCode": "en-US"
      },
      "primaryType": "church",
      "shortFormattedAddress": "768F+J7C, Suchen Mulieh"
    }
  ]
}

