{
  "places_with_reviews": [
    {
      "name": "Hotel Bliss",
      "rating": [
        3.5
      ],
      "address": [
        "Lazibal, KP Rd, Sadiq Abad, Anantnag, 192101"
      ],
      "reviews": [
        {
          "text": "It was expensive. Staff behaviour wasn't welcoming. The hearing system wasn't working properly. Issues with the Hotel water. Overall the service wasn't good at all.",
          "languageCode": "en",
          "rating": [
            3.5
          ]
        },
        {
          "text": "We booked  13 August 2023 two rooms in this hotel bliss very very experience with in half a hour called staff to fix both rooms toilets also one room ac stoped call again to fix staff had attitude big time than decided few family members went to our relatives home. Next morning trying to take shower same thing happened in the middle water stopped coming through tap. Wifi was working whole time. Even I talked their manager explain everything about last night and morning. I won\u2019t go there again. Don\u2019t give these kind people any business they don\u2019t deserve. Big no thumb down to their service. Before booking think about going to have good time worse experience shame on them",
          "languageCode": "en",
          "rating": [
            3.5
          ]
        },
        {
          "text": "Good food. Good location and nice service",
          "languageCode": "en",
          "rating": [
            3.5
          ]
        },
        {
          "text": "Ever worst service as well as hotel management. No one at Reception from 10pm to 9am.\nNo towel soap in washroom,\nNo complimentary water available.",
          "languageCode": "en",
          "rating": [
            3.5
          ]
        },
        {
          "text": "Forgot to take top roof view, it\u2019s good place for staying cause got super supported warm shower water n it\u2019s located on the road side. Recommend",
          "languageCode": "en",
          "rating": [
            3.5
          ]
        }
      ]
    },
    {
      "name": "Pinez Guest House - Best Hotel in Anantnag",
      "rating": [
        4.4
      ],
      "address": [
        "Khanabal, Anantnag, 192101"
      ],
      "reviews": [
        {
          "text": "Best and trusted hotel for family and bachelor\u2019s in anantnag\nRooms are neat and clean.\nHeater blankets and room heater are there which is very helpful during winter times.\nReceptionist and Manager were very friendly.",
          "languageCode": "en",
          "rating": [
            4.4
          ]
        },
        {
          "text": "Superb stay. Neat and clean rooms . Very polite staff.",
          "languageCode": "en",
          "rating": [
            4.4
          ]
        },
        {
          "text": "Located in a silent area,rooms are spacious  enough with clean bed having excellent ventilation with fan and tv.Bath room cleanliness can be improved though accessories are comfortable with working geyser and I paid 1000 rupees for single occupancy and choice is limited in Anantnag.",
          "languageCode": "en",
          "rating": [
            4.4
          ]
        },
        {
          "text": "I want to know,is this a couple friendly hotel like can we stay here with girlfriend",
          "languageCode": "en",
          "rating": [
            4.4
          ]
        },
        {
          "text": "This is a good option to stay overnight if you are travelling or are in a vacation. Not recommended for a long 2-3 or more days of stay as there are other better options, however for a overnight stay it is perfect!",
          "languageCode": "en",
          "rating": [
            4.4
          ]
        }
      ]
    },
    {
      "name": "JANNAT HOTEL & RESTAURANT",
      "rating": [
        3.1
      ],
      "address": [
        "Khanabal, Anantnag, 192101"
      ],
      "reviews": [
        {
          "text": "There is very vad facilities and owner behaviour too stupid\nDon't stay there",
          "languageCode": "en",
          "rating": [
            3.1
          ]
        },
        {
          "text": "V good",
          "languageCode": "en",
          "rating": [
            3.1
          ]
        },
        {
          "text": "Great place to visit",
          "languageCode": "en",
          "rating": [
            3.1
          ]
        },
        {
          "text": "Gohar Bhai is very good brother.",
          "languageCode": "en-US",
          "rating": [
            3.1
          ]
        }
      ]
    },
    {
      "name": "Springs Mall",
      "rating": [
        4
      ],
      "address": [
        "KP Rd, Lazibal, Anantnag, 192101"
      ],
      "reviews": [
        {
          "text": "Food was good.\nService also good, need to be improved.\nRecommend to visit.\nAlso at good location",
          "languageCode": "en",
          "rating": [
            4
          ]
        },
        {
          "text": "You have plenty of options for shopping and food. Parking is available",
          "languageCode": "en",
          "rating": [
            4
          ]
        },
        {
          "text": "Fabulous... outstanding... very tasty food....good service\nNice environment\nMust visit.....",
          "languageCode": "en",
          "rating": [
            4
          ]
        },
        {
          "text": "Too much expensive.They too lure with offers buying of two getting one free but price is adjusted accordingly.if one need to buy only one he will definitely end up buying two.what is the fun,when our economy is already hit very badly.The society can afford only buying one not two.They can launch 50% discount having a great alternative.",
          "languageCode": "en",
          "rating": [
            4
          ]
        },
        {
          "text": "Zabar 10 , a place, where from u can get everything, food, clothes sweets etc...",
          "languageCode": "en",
          "rating": [
            4
          ]
        }
      ]
    },
    {
      "name": "Hotel Vivek",
      "rating": [
        3.7
      ],
      "address": [
        "P4PW+7JG, General Bus Stand Rd, Hussainabad, jammu, Anantnag, 180001"
      ],
      "reviews": [
        {
          "text": "Very nice",
          "languageCode": "en",
          "rating": [
            3.7
          ]
        },
        {
          "text": "Very beautiful hotel well maintained\nServices are very good and restaurant is very beautiful.staff friendly. Very tasty cooking variety is available here including wazwan",
          "languageCode": "en",
          "rating": [
            3.7
          ]
        },
        {
          "text": "Very good hotel and well maintained..and have a good staff.. people can book online room or on call..",
          "languageCode": "en",
          "rating": [
            3.7
          ]
        },
        {
          "text": "Hotel was good and well maintained. The staff and specially the owner welcomes you with a great honour.",
          "languageCode": "en",
          "rating": [
            3.7
          ]
        },
        {
          "text": "Good Service with delicious and hygienic food",
          "languageCode": "en",
          "rating": [
            3.7
          ]
        }
      ]
    },
    {
      "name": "hilltop",
      "rating": [
        3
      ],
      "address": [
        "P429+4Q4, pahalgam, 192101"
      ],
      "reviews": [
        {
          "text": "Best hotel",
          "languageCode": "en",
          "rating": [
            3
          ]
        },
        {
          "text": "Nice",
          "languageCode": "en",
          "rating": [
            3
          ]
        }
      ]
    },
    {
      "name": "Bhat Muslim Hotel",
      "rating": [
        "Unknown"
      ],
      "address": [
        "NH 44, Alstop, 192101"
      ],
      "reviews": []
    },
    {
      "name": "Fahad's house",
      "rating": [
        5
      ],
      "address": [
        "Gulshan Abad Sarnal, Gulshanabad, Sarnal, Anantnag, 192101"
      ],
      "reviews": []
    },
    {
      "name": "Rohella guest house Rafi",
      "rating": [
        3
      ],
      "address": [
        "Banghidar, Anantnag, 192126"
      ],
      "reviews": [
        {
          "text": "Normal quality",
          "languageCode": "en",
          "rating": [
            3
          ]
        }
      ]
    },
    {
      "name": "Sam fast food & hot spot",
      "rating": [
        4
      ],
      "address": [
        "KP Rd, Gulshan Abad Sarnal, Gulshanabad, Sarnal, Anantnag, 192101"
      ],
      "reviews": [
        {
          "text": "Delicious and tasty food",
          "languageCode": "en",
          "rating": [
            4
          ]
        },
        {
          "text": "Amazing quality nd products available \ud83d\ude42\ud83d\ude42\ud83d\ude42\ud83d\ude42\ud83d\ude42\ud83d\ude42\ud83d\ude42",
          "languageCode": "en",
          "rating": [
            4
          ]
        },
        {
          "text": "Tasty",
          "languageCode": "en",
          "rating": [
            4
          ]
        }
      ]
    }
  ]
}